{"ta":"MAL","tb":"PAN","timeline":[{"e":68,"s":2332,"a":2,"b":2,"w":0.5,"p":1,"d":"GIST, JAMES (PAN) \u2014 Layup Made (1/1 -  2 pt)"},{"e":203,"s":2197,"a":4,"b":2,"w":0.5379,"p":1,"d":"VAZQUEZ, FRAN (MAL) \u2014 Layup Made (1/4 -  2 pt)"},{"e":235,"s":2165,"a":6,"b":2,"w":0.576,"p":1,"d":"VAZQUEZ, FRAN (MAL) \u2014 Two Pointer (2/5 -  4 pt)"},{"e":258,"s":2142,"a":6,"b":5,"w":0.5192,"p":1,"d":"MACIULIS, JONAS (PAN) \u2014 Three Pointer (1/1 -  3 pt)"},{"e":286,"s":2114,"a":6,"b":8,"w":0.4613,"p":1,"d":"UKIC, ROKO (PAN) \u2014 Three Pointer (1/1 -  3 pt)"},{"e":372,"s":2028,"a":8,"b":8,"w":0.5,"p":1,"d":"VAZQUEZ, FRAN (MAL) \u2014 Two Pointer (3/7 -  6 pt)"},{"e":396,"s":2004,"a":8,"b":11,"w":0.4406,"p":1,"d":"MACIULIS, JONAS (PAN) \u2014 Three Pointer (2/2 -  6 pt)"},{"e":481,"s":1919,"a":8,"b":14,"w":0.3804,"p":1,"d":"DIAMANTIDIS, DIMITRIS (PAN) \u2014 Three Pointer (1/1 -  3 pt)"},{"e":599,"s":1801,"a":8,"b":16,"w":0.3381,"p":1,"d":"SCHORTSANITIS, SOFOKLIS (PAN) \u2014 Layup Made (1/1 -  2 pt)"},{"e":615,"s":1785,"a":10,"b":16,"w":0.3761,"p":2,"d":"ZORIC, LUKA (MAL) \u2014 Layup Made (2/3 -  4 pt)"},{"e":647,"s":1753,"a":13,"b":16,"w":0.4365,"p":2,"d":"WILLIAMS, MARCUS (MAL) \u2014 Three Pointer (1/1 -  3 pt)"},{"e":758,"s":1642,"a":13,"b":18,"w":0.3918,"p":2,"d":"LASME, STEPHANE (PAN) \u2014 Dunk (1/2 -  2 pt)"},{"e":787,"s":1613,"a":15,"b":18,"w":0.4339,"p":2,"d":"WILLIAMS, MARCUS (MAL) \u2014 Two Pointer (1/1 -  5 pt)"},{"e":852,"s":1548,"a":15,"b":19,"w":0.4104,"p":2,"d":"MACIULIS, JONAS (PAN) \u2014 Free Throw In (1/1 -  7 pt)"},{"e":864,"s":1536,"a":15,"b":20,"w":0.3883,"p":2,"d":"BANKS, MARCUS (PAN) \u2014 Free Throw In (1/1 -  1 pt)"},{"e":864,"s":1536,"a":15,"b":21,"w":0.3669,"p":2,"d":"BANKS, MARCUS (PAN) \u2014 Free Throw In (2/2 -  2 pt)"},{"e":895,"s":1505,"a":15,"b":23,"w":0.3242,"p":2,"d":"GIST, JAMES (PAN) \u2014 Dunk (2/3 -  4 pt)"},{"e":942,"s":1458,"a":17,"b":23,"w":0.3636,"p":2,"d":"CALLOWAY, EARL (MAL) \u2014 Two Pointer (1/3 -  2 pt)"},{"e":981,"s":1419,"a":20,"b":23,"w":0.4295,"p":2,"d":"SIMON, KRUNOSLAV (MAL) \u2014 Three Pointer (1/4 -  3 pt)"},{"e":998,"s":1402,"a":20,"b":24,"w":0.406,"p":2,"d":"DIAMANTIDIS, DIMITRIS (PAN) \u2014 Free Throw In (1/1 -  4 pt)"},{"e":998,"s":1402,"a":20,"b":25,"w":0.3833,"p":2,"d":"DIAMANTIDIS, DIMITRIS (PAN) \u2014 Free Throw In (2/2 -  5 pt)"},{"e":1016,"s":1384,"a":22,"b":25,"w":0.4287,"p":2,"d":"ZORIC, LUKA (MAL) \u2014 Layup Made (3/5 -  6 pt)"},{"e":1021,"s":1379,"a":22,"b":28,"w":0.3599,"p":2,"d":"GIST, JAMES (PAN) \u2014 Three Pointer (1/2 -  7 pt)"},{"e":1104,"s":1296,"a":22,"b":29,"w":0.3334,"p":2,"d":"LASME, STEPHANE (PAN) \u2014 Free Throw In (1/1 -  3 pt)"},{"e":1104,"s":1296,"a":22,"b":30,"w":0.3118,"p":2,"d":"LASME, STEPHANE (PAN) \u2014 Free Throw In (2/2 -  4 pt)"},{"e":1120,"s":1280,"a":24,"b":30,"w":0.3549,"p":2,"d":"VAZQUEZ, FRAN (MAL) \u2014 Layup Made (4/8 -  8 pt)"},{"e":1137,"s":1263,"a":24,"b":32,"w":0.3096,"p":2,"d":"TSARTSARIS, KOSTAS (PAN) \u2014 Layup Made (1/1 -  2 pt)"},{"e":1176,"s":1224,"a":24,"b":34,"w":0.2653,"p":2,"d":"UKIC, ROKO (PAN) \u2014 Two Pointer (1/2 -  5 pt)"},{"e":1193,"s":1207,"a":25,"b":34,"w":0.2844,"p":2,"d":"WILLIAMS, MARCUS (MAL) \u2014 Free Throw In (1/1 -  6 pt)"},{"e":1193,"s":1207,"a":26,"b":34,"w":0.3057,"p":2,"d":"WILLIAMS, MARCUS (MAL) \u2014 Free Throw In (2/2 -  7 pt)"},{"e":1198,"s":1202,"a":26,"b":35,"w":0.284,"p":2,"d":"UKIC, ROKO (PAN) \u2014 Free Throw In (1/1 -  6 pt)"},{"e":1214,"s":1186,"a":26,"b":38,"w":0.2242,"p":3,"d":"MACIULIS, JONAS (PAN) \u2014 Three Pointer (3/5 -  10 pt)"},{"e":1240,"s":1160,"a":28,"b":38,"w":0.26,"p":3,"d":"ZORIC, LUKA (MAL) \u2014 Layup Made (4/6 -  8 pt)"},{"e":1274,"s":1126,"a":30,"b":38,"w":0.2996,"p":3,"d":"ZORIC, LUKA (MAL) \u2014 Layup Made (5/7 -  10 pt)"},{"e":1310,"s":1090,"a":32,"b":38,"w":0.3436,"p":3,"d":"SIMON, KRUNOSLAV (MAL) \u2014 Layup Made (1/4 -  5 pt)"},{"e":1310,"s":1090,"a":33,"b":38,"w":0.3683,"p":3,"d":"SIMON, KRUNOSLAV (MAL) \u2014 Free Throw In (1/1 -  6 pt)"},{"e":1377,"s":1023,"a":35,"b":38,"w":0.4172,"p":3,"d":"ZORIC, LUKA (MAL) \u2014 Layup Made (6/8 -  12 pt)"},{"e":1401,"s":999,"a":35,"b":41,"w":0.3371,"p":3,"d":"MACIULIS, JONAS (PAN) \u2014 Three Pointer (4/6 -  13 pt)"},{"e":1480,"s":920,"a":38,"b":41,"w":0.4128,"p":3,"d":"CALLOWAY, EARL (MAL) \u2014 Three Pointer (1/2 -  5 pt)"},{"e":1490,"s":910,"a":38,"b":44,"w":0.3299,"p":3,"d":"UKIC, ROKO (PAN) \u2014 Three Pointer (2/3 -  9 pt)"},{"e":1541,"s":859,"a":40,"b":44,"w":0.3808,"p":3,"d":"URTASUN, TXEMI (MAL) \u2014 Two Pointer (1/4 -  2 pt)"},{"e":1572,"s":828,"a":40,"b":46,"w":0.3224,"p":3,"d":"LASME, STEPHANE (PAN) \u2014 Layup Made (2/6 -  6 pt)"},{"e":1596,"s":804,"a":42,"b":46,"w":0.3769,"p":3,"d":"VAZQUEZ, FRAN (MAL) \u2014 Layup Made (5/11 -  10 pt)"},{"e":1596,"s":804,"a":43,"b":46,"w":0.4069,"p":3,"d":"VAZQUEZ, FRAN (MAL) \u2014 Free Throw In (1/1 -  11 pt)"},{"e":1651,"s":749,"a":43,"b":48,"w":0.3428,"p":3,"d":"SCHORTSANITIS, SOFOKLIS (PAN) \u2014 Layup Made (2/2 -  4 pt)"},{"e":1671,"s":729,"a":44,"b":48,"w":0.371,"p":3,"d":"URTASUN, TXEMI (MAL) \u2014 Free Throw In (1/2 -  3 pt)"},{"e":1723,"s":677,"a":44,"b":51,"w":0.2772,"p":3,"d":"UKIC, ROKO (PAN) \u2014 Three Pointer (3/4 -  12 pt)"},{"e":1798,"s":602,"a":44,"b":53,"w":0.213,"p":3,"d":"SCHORTSANITIS, SOFOKLIS (PAN) \u2014 Layup Made (3/4 -  6 pt)"},{"e":1810,"s":590,"a":47,"b":53,"w":0.2932,"p":4,"d":"WILLIAMS, MARCUS (MAL) \u2014 Three Pointer (2/3 -  10 pt)"},{"e":1823,"s":577,"a":48,"b":53,"w":0.3226,"p":4,"d":"WILLIAMS, MARCUS (MAL) \u2014 Free Throw In (3/3 -  11 pt)"},{"e":1835,"s":565,"a":50,"b":53,"w":0.3894,"p":4,"d":"WILLIAMS, MARCUS (MAL) \u2014 Two Pointer (2/5 -  13 pt)"},{"e":1935,"s":465,"a":51,"b":53,"w":0.4181,"p":4,"d":"VAZQUEZ, FRAN (MAL) \u2014 Free Throw In (2/2 -  12 pt)"},{"e":1935,"s":465,"a":52,"b":53,"w":0.4588,"p":4,"d":"VAZQUEZ, FRAN (MAL) \u2014 Free Throw In (3/3 -  13 pt)"},{"e":1952,"s":448,"a":52,"b":55,"w":0.3764,"p":4,"d":"MACIULIS, JONAS (PAN) \u2014 Two Pointer (1/3 -  15 pt)"},{"e":1991,"s":409,"a":52,"b":58,"w":0.2579,"p":4,"d":"DIAMANTIDIS, DIMITRIS (PAN) \u2014 Three Pointer (2/3 -  8 pt)"},{"e":2011,"s":389,"a":55,"b":58,"w":0.3677,"p":4,"d":"SIMON, KRUNOSLAV (MAL) \u2014 Three Pointer (2/7 -  9 pt)"},{"e":2114,"s":286,"a":55,"b":59,"w":0.301,"p":4,"d":"UKIC, ROKO (PAN) \u2014 Free Throw In (2/3 -  13 pt)"},{"e":2114,"s":286,"a":55,"b":60,"w":0.2586,"p":4,"d":"UKIC, ROKO (PAN) \u2014 Free Throw In (3/4 -  14 pt)"},{"e":2220,"s":180,"a":60,"b":60,"w":0.5,"p":4,"d":"WILLIAMS, MARCUS (MAL) \u2014 Three Pointer (3/5 -  16 pt)"},{"e":2237,"s":163,"a":57,"b":60,"w":0.3021,"p":4,"d":"ZORIC, LUKA (MAL) \u2014 Layup Made (7/10 -  14 pt)"},{"e":2318,"s":82,"a":63,"b":60,"w":0.765,"p":4,"d":"WILLIAMS, MARCUS (MAL) \u2014 Three Pointer (4/6 -  19 pt)"},{"e":2379,"s":21,"a":66,"b":60,"w":0.9907,"p":4,"d":"WILLIAMS, MARCUS (MAL) \u2014 Three Pointer (5/7 -  22 pt)"},{"e":2400,"s":0,"a":66,"b":60,"w":1.0,"p":4,"d":"Final Buzzer"}],"adv":{"q":[{"p":1,"a":8,"b":16},{"p":2,"a":18,"b":19},{"p":3,"a":18,"b":18},{"p":4,"a":22,"b":7}],"i":[{"n":"Banks","p":2,"h":0,"t":"PAN"},{"n":"Bramos","p":0,"h":6,"t":"PAN"},{"n":"Calloway","p":5,"h":5,"t":"MAL"},{"n":"Diamantidis","p":8,"h":12,"t":"PAN"},{"n":"Gist","p":3,"h":11,"t":"PAN"},{"n":"Lasme","p":2,"h":7,"t":"PAN"},{"n":"Maciulis","p":15,"h":0,"t":"PAN"},{"n":"Panko","p":0,"h":3,"t":"MAL"},{"n":"Perovic","p":0,"h":3,"t":"MAL"},{"n":"Schortsanitis","p":0,"h":1,"t":"PAN"},{"n":"Simon","p":7,"h":5,"t":"MAL"},{"n":"Tsartsaris","p":0,"h":3,"t":"PAN"},{"n":"Ukic","p":14,"h":7,"t":"PAN"},{"n":"Urtasun","p":3,"h":3,"t":"MAL"},{"n":"Vazquez","p":7,"h":6,"t":"MAL"},{"n":"Vidal","p":0,"h":5,"t":"MAL"},{"n":"Williams","p":22,"h":5,"t":"MAL"},{"n":"Zoric","p":2,"h":10,"t":"MAL"}]}}