{"ta":"BAS","tb":"TEL","timeline":[{"e":63,"s":2337,"a":3,"b":2,"w":0.5184,"p":1,"d":"WOLTERS, NATE (TEL) \u2014 Two Pointer (1/2 -  2 pt)"},{"e":129,"s":2271,"a":3,"b":4,"w":0.4813,"p":1,"d":"ZOOSMAN, YOVEL (TEL) \u2014 Two Pointer (1/1 -  2 pt)"},{"e":155,"s":2245,"a":5,"b":4,"w":0.5188,"p":1,"d":"ERIC, MICHAEL (BAS) \u2014 Two Pointer (1/1 -  2 pt)"},{"e":172,"s":2228,"a":5,"b":7,"w":0.4623,"p":1,"d":"ACY, QUINCY (TEL) \u2014 Three Pointer (1/1 -  3 pt)"},{"e":195,"s":2205,"a":6,"b":7,"w":0.481,"p":1,"d":"GARINO, PATRICIO (BAS) \u2014 Free Throw In (1/1 -  1 pt)"},{"e":195,"s":2205,"a":7,"b":7,"w":0.5,"p":1,"d":"GARINO, PATRICIO (BAS) \u2014 Free Throw In (2/2 -  2 pt)"},{"e":211,"s":2189,"a":7,"b":8,"w":0.481,"p":1,"d":"BLACK, TARIK (TEL) \u2014 Free Throw In (1/1 -  1 pt)"},{"e":244,"s":2156,"a":7,"b":10,"w":0.4427,"p":1,"d":"BLACK, TARIK (TEL) \u2014 Two Pointer (1/1 -  3 pt)"},{"e":282,"s":2118,"a":7,"b":13,"w":0.3859,"p":1,"d":"WILBEKIN, SCOTTIE (TEL) \u2014 Three Pointer (1/2 -  3 pt)"},{"e":312,"s":2088,"a":9,"b":13,"w":0.4227,"p":1,"d":"FALL, YOUSSOUPHA (BAS) \u2014 Two Pointer (1/1 -  2 pt)"},{"e":329,"s":2071,"a":9,"b":16,"w":0.3663,"p":1,"d":"WILBEKIN, SCOTTIE (TEL) \u2014 Three Pointer (2/3 -  6 pt)"},{"e":339,"s":2061,"a":10,"b":16,"w":0.3844,"p":1,"d":"VILDOZA, LUCA (BAS) \u2014 Free Throw In (1/1 -  1 pt)"},{"e":339,"s":2061,"a":11,"b":16,"w":0.4031,"p":1,"d":"VILDOZA, LUCA (BAS) \u2014 Free Throw In (2/2 -  2 pt)"},{"e":375,"s":2025,"a":11,"b":17,"w":0.3834,"p":1,"d":"WILBEKIN, SCOTTIE (TEL) \u2014 Free Throw In (1/1 -  7 pt)"},{"e":375,"s":2025,"a":11,"b":18,"w":0.3649,"p":1,"d":"WILBEKIN, SCOTTIE (TEL) \u2014 Free Throw In (2/2 -  8 pt)"},{"e":396,"s":2004,"a":13,"b":18,"w":0.4018,"p":1,"d":"SHENGELIA, TORNIKE (BAS) \u2014 Two Pointer (1/2 -  5 pt)"},{"e":419,"s":1981,"a":14,"b":18,"w":0.4206,"p":1,"d":"HENRY, PIERRIA (BAS) \u2014 Free Throw In (1/2 -  1 pt)"},{"e":443,"s":1957,"a":17,"b":18,"w":0.4799,"p":1,"d":"SHENGELIA, TORNIKE (BAS) \u2014 Three Pointer (2/3 -  8 pt)"},{"e":457,"s":1943,"a":17,"b":20,"w":0.4397,"p":1,"d":"DIBARTOLOMEO, JOHN (TEL) \u2014 Two Pointer (1/1 -  2 pt)"},{"e":474,"s":1926,"a":18,"b":20,"w":0.4595,"p":1,"d":"HENRY, PIERRIA (BAS) \u2014 Free Throw In (2/3 -  2 pt)"},{"e":500,"s":1900,"a":18,"b":23,"w":0.3992,"p":1,"d":"DIBARTOLOMEO, JOHN (TEL) \u2014 Three Pointer (1/1 -  5 pt)"},{"e":531,"s":1869,"a":18,"b":26,"w":0.3409,"p":1,"d":"DIBARTOLOMEO, JOHN (TEL) \u2014 Three Pointer (2/2 -  8 pt)"},{"e":560,"s":1840,"a":18,"b":28,"w":0.3035,"p":1,"d":"ZOOSMAN, YOVEL (TEL) \u2014 Two Pointer (2/2 -  4 pt)"},{"e":571,"s":1829,"a":19,"b":28,"w":0.3209,"p":1,"d":"STAUSKAS, NIK (BAS) \u2014 Free Throw In (1/1 -  1 pt)"},{"e":590,"s":1810,"a":21,"b":28,"w":0.3575,"p":1,"d":"HENRY, PIERRIA (BAS) \u2014 Two Pointer (1/1 -  4 pt)"},{"e":630,"s":1770,"a":22,"b":28,"w":0.3756,"p":2,"d":"STAUSKAS, NIK (BAS) \u2014 Free Throw In (2/3 -  2 pt)"},{"e":656,"s":1744,"a":22,"b":30,"w":0.3357,"p":2,"d":"DIBARTOLOMEO, JOHN (TEL) \u2014 Two Pointer (2/2 -  10 pt)"},{"e":663,"s":1737,"a":23,"b":30,"w":0.3547,"p":2,"d":"STAUSKAS, NIK (BAS) \u2014 Free Throw In (3/4 -  3 pt)"},{"e":663,"s":1737,"a":24,"b":30,"w":0.3745,"p":2,"d":"STAUSKAS, NIK (BAS) \u2014 Free Throw In (4/6 -  4 pt)"},{"e":680,"s":1720,"a":24,"b":33,"w":0.3158,"p":2,"d":"WILBEKIN, SCOTTIE (TEL) \u2014 Three Pointer (3/4 -  11 pt)"},{"e":744,"s":1656,"a":24,"b":36,"w":0.2591,"p":2,"d":"WILBEKIN, SCOTTIE (TEL) \u2014 Three Pointer (4/5 -  14 pt)"},{"e":876,"s":1524,"a":24,"b":39,"w":0.2028,"p":2,"d":"WILBEKIN, SCOTTIE (TEL) \u2014 Three Pointer (5/6 -  17 pt)"},{"e":896,"s":1504,"a":27,"b":39,"w":0.2493,"p":2,"d":"SHENGELIA, TORNIKE (BAS) \u2014 Three Pointer (3/5 -  11 pt)"},{"e":911,"s":1489,"a":27,"b":41,"w":0.2154,"p":2,"d":"WOLTERS, NATE (TEL) \u2014 Two Pointer (2/3 -  4 pt)"},{"e":951,"s":1449,"a":27,"b":43,"w":0.1828,"p":2,"d":"HUNTER, OTHELLO (TEL) \u2014 Two Pointer (1/3 -  2 pt)"},{"e":1002,"s":1398,"a":27,"b":45,"w":0.1525,"p":2,"d":"HUNTER, OTHELLO (TEL) \u2014 Two Pointer (2/4 -  4 pt)"},{"e":1028,"s":1372,"a":29,"b":45,"w":0.1767,"p":2,"d":"SHENGELIA, TORNIKE (BAS) \u2014 Two Pointer (2/4 -  13 pt)"},{"e":1048,"s":1352,"a":29,"b":47,"w":0.1488,"p":2,"d":"BLACK, TARIK (TEL) \u2014 Two Pointer (2/2 -  5 pt)"},{"e":1048,"s":1352,"a":29,"b":48,"w":0.1369,"p":2,"d":"BLACK, TARIK (TEL) \u2014 Free Throw In (2/3 -  6 pt)"},{"e":1081,"s":1319,"a":29,"b":50,"w":0.113,"p":2,"d":"BRYANT, ELIJAH (TEL) \u2014 Two Pointer (1/2 -  2 pt)"},{"e":1091,"s":1309,"a":31,"b":50,"w":0.1334,"p":2,"d":"GARINO, PATRICIO (BAS) \u2014 Two Pointer (1/1 -  4 pt)"},{"e":1091,"s":1309,"a":32,"b":50,"w":0.1452,"p":2,"d":"GARINO, PATRICIO (BAS) \u2014 Free Throw In (3/3 -  5 pt)"},{"e":1110,"s":1290,"a":32,"b":53,"w":0.1107,"p":2,"d":"BRYANT, ELIJAH (TEL) \u2014 Three Pointer (1/2 -  5 pt)"},{"e":1173,"s":1227,"a":32,"b":55,"w":0.0879,"p":2,"d":"HUNTER, OTHELLO (TEL) \u2014 Two Pointer (3/5 -  6 pt)"},{"e":1220,"s":1180,"a":32,"b":57,"w":0.0696,"p":3,"d":"BLACK, TARIK (TEL) \u2014 Two Pointer (3/3 -  8 pt)"},{"e":1239,"s":1161,"a":33,"b":57,"w":0.0752,"p":3,"d":"SHENGELIA, TORNIKE (BAS) \u2014 Free Throw In (1/1 -  14 pt)"},{"e":1239,"s":1161,"a":34,"b":57,"w":0.0828,"p":3,"d":"SHENGELIA, TORNIKE (BAS) \u2014 Free Throw In (2/2 -  15 pt)"},{"e":1258,"s":1142,"a":34,"b":59,"w":0.0669,"p":3,"d":"WOLTERS, NATE (TEL) \u2014 Two Pointer (3/4 -  6 pt)"},{"e":1312,"s":1088,"a":34,"b":62,"w":0.0463,"p":3,"d":"WOLTERS, NATE (TEL) \u2014 Three Pointer (1/1 -  9 pt)"},{"e":1345,"s":1055,"a":34,"b":65,"w":0.0323,"p":3,"d":"WILBEKIN, SCOTTIE (TEL) \u2014 Three Pointer (6/7 -  20 pt)"},{"e":1364,"s":1036,"a":36,"b":65,"w":0.0388,"p":3,"d":"GARINO, PATRICIO (BAS) \u2014 Two Pointer (2/2 -  7 pt)"},{"e":1386,"s":1014,"a":36,"b":67,"w":0.0302,"p":3,"d":"ACY, QUINCY (TEL) \u2014 Two Pointer (1/1 -  5 pt)"},{"e":1401,"s":999,"a":39,"b":67,"w":0.0408,"p":3,"d":"GARINO, PATRICIO (BAS) \u2014 Three Pointer (1/1 -  10 pt)"},{"e":1423,"s":977,"a":41,"b":67,"w":0.0491,"p":3,"d":"SHENGELIA, TORNIKE (BAS) \u2014 Two Pointer (3/6 -  17 pt)"},{"e":1440,"s":960,"a":41,"b":70,"w":0.0344,"p":3,"d":"WOLTERS, NATE (TEL) \u2014 Three Pointer (2/2 -  12 pt)"},{"e":1472,"s":928,"a":44,"b":70,"w":0.0456,"p":3,"d":"SHENGELIA, TORNIKE (BAS) \u2014 Three Pointer (4/6 -  20 pt)"},{"e":1496,"s":904,"a":44,"b":73,"w":0.0312,"p":3,"d":"DIBARTOLOMEO, JOHN (TEL) \u2014 Three Pointer (3/3 -  13 pt)"},{"e":1513,"s":887,"a":46,"b":73,"w":0.0381,"p":3,"d":"GARINO, PATRICIO (BAS) \u2014 Two Pointer (3/4 -  12 pt)"},{"e":1529,"s":871,"a":46,"b":75,"w":0.0293,"p":3,"d":"BRYANT, ELIJAH (TEL) \u2014 Two Pointer (2/3 -  7 pt)"},{"e":1548,"s":852,"a":46,"b":77,"w":0.0222,"p":3,"d":"BRYANT, ELIJAH (TEL) \u2014 Two Pointer (3/4 -  9 pt)"},{"e":1565,"s":835,"a":49,"b":77,"w":0.0307,"p":3,"d":"GARINO, PATRICIO (BAS) \u2014 Three Pointer (2/2 -  15 pt)"},{"e":1582,"s":818,"a":49,"b":80,"w":0.0206,"p":3,"d":"BRYANT, ELIJAH (TEL) \u2014 Three Pointer (2/4 -  12 pt)"},{"e":1650,"s":750,"a":52,"b":80,"w":0.0255,"p":3,"d":"GARINO, PATRICIO (BAS) \u2014 Three Pointer (3/3 -  18 pt)"},{"e":1688,"s":712,"a":53,"b":80,"w":0.0265,"p":3,"d":"HENRY, PIERRIA (BAS) \u2014 Free Throw In (3/6 -  5 pt)"},{"e":1700,"s":700,"a":53,"b":82,"w":0.0197,"p":3,"d":"BRYANT, ELIJAH (TEL) \u2014 Two Pointer (4/5 -  14 pt)"},{"e":1741,"s":659,"a":53,"b":85,"w":0.0116,"p":3,"d":"DORSEY, TYLER (TEL) \u2014 Three Pointer (1/3 -  3 pt)"},{"e":1759,"s":641,"a":55,"b":85,"w":0.0145,"p":3,"d":"SHENGELIA, TORNIKE (BAS) \u2014 Two Pointer (4/8 -  22 pt)"},{"e":1759,"s":641,"a":56,"b":85,"w":0.0166,"p":3,"d":"SHENGELIA, TORNIKE (BAS) \u2014 Free Throw In (3/3 -  23 pt)"},{"e":1792,"s":608,"a":57,"b":85,"w":0.0172,"p":3,"d":"HENRY, PIERRIA (BAS) \u2014 Free Throw In (4/7 -  6 pt)"},{"e":1792,"s":608,"a":58,"b":85,"w":0.0198,"p":3,"d":"HENRY, PIERRIA (BAS) \u2014 Free Throw In (5/8 -  7 pt)"},{"e":1800,"s":600,"a":58,"b":86,"w":0.0167,"p":3,"d":"DIBARTOLOMEO, JOHN (TEL) \u2014 Free Throw In (1/1 -  14 pt)"},{"e":1815,"s":585,"a":61,"b":86,"w":0.0245,"p":4,"d":"STAUSKAS, NIK (BAS) \u2014 Three Pointer (1/3 -  7 pt)"},{"e":1845,"s":555,"a":61,"b":88,"w":0.0166,"p":4,"d":"BRYANT, ELIJAH (TEL) \u2014 Two Pointer (5/6 -  16 pt)"},{"e":1884,"s":516,"a":61,"b":90,"w":0.0105,"p":4,"d":"DORSEY, TYLER (TEL) \u2014 Two Pointer (1/3 -  5 pt)"},{"e":1884,"s":516,"a":61,"b":93,"w":0.0066,"p":4,"d":"DORSEY, TYLER (TEL) \u2014 Three Pointer (2/5 -  8 pt)"},{"e":1905,"s":495,"a":64,"b":93,"w":0.0095,"p":4,"d":"GARINO, PATRICIO (BAS) \u2014 Three Pointer (4/4 -  21 pt)"},{"e":1924,"s":476,"a":65,"b":93,"w":0.0102,"p":4,"d":"GARINO, PATRICIO (BAS) \u2014 Free Throw In (4/5 -  22 pt)"},{"e":1924,"s":476,"a":66,"b":93,"w":0.012,"p":4,"d":"GARINO, PATRICIO (BAS) \u2014 Free Throw In (5/6 -  23 pt)"},{"e":1966,"s":434,"a":66,"b":95,"w":0.007,"p":4,"d":"WOLTERS, NATE (TEL) \u2014 Two Pointer (4/5 -  14 pt)"},{"e":2085,"s":315,"a":66,"b":97,"w":0.002,"p":4,"d":"HUNTER, OTHELLO (TEL) \u2014 Two Pointer (4/6 -  8 pt)"},{"e":2096,"s":304,"a":69,"b":97,"w":0.0033,"p":4,"d":"SHENGELIA, TORNIKE (BAS) \u2014 Three Pointer (5/7 -  26 pt)"},{"e":2115,"s":285,"a":69,"b":99,"w":0.0018,"p":4,"d":"COHEN, JAKE (TEL) \u2014 Two Pointer (1/2 -  2 pt)"},{"e":2134,"s":266,"a":69,"b":101,"w":0.0009,"p":4,"d":"DORSEY, TYLER (TEL) \u2014 Two Pointer (2/4 -  10 pt)"},{"e":2149,"s":251,"a":71,"b":101,"w":0.0012,"p":4,"d":"SHENGELIA, TORNIKE (BAS) \u2014 Two Pointer (5/9 -  28 pt)"},{"e":2171,"s":229,"a":72,"b":101,"w":0.0011,"p":4,"d":"POLONARA, ACHILLE (BAS) \u2014 Free Throw In (1/1 -  1 pt)"},{"e":2171,"s":229,"a":73,"b":101,"w":0.0014,"p":4,"d":"POLONARA, ACHILLE (BAS) \u2014 Free Throw In (2/2 -  2 pt)"},{"e":2182,"s":218,"a":74,"b":101,"w":0.0015,"p":4,"d":"GARINO, PATRICIO (BAS) \u2014 Free Throw In (6/7 -  24 pt)"},{"e":2232,"s":168,"a":74,"b":103,"w":0.0003,"p":4,"d":"HUNTER, OTHELLO (TEL) \u2014 Two Pointer (5/7 -  10 pt)"},{"e":2278,"s":122,"a":74,"b":106,"w":0.0,"p":4,"d":"BRYANT, ELIJAH (TEL) \u2014 Three Pointer (3/6 -  19 pt)"},{"e":2289,"s":111,"a":75,"b":106,"w":0.0,"p":4,"d":"JANNING, MATT (BAS) \u2014 Free Throw In (1/1 -  1 pt)"},{"e":2289,"s":111,"a":76,"b":106,"w":0.0,"p":4,"d":"JANNING, MATT (BAS) \u2014 Free Throw In (2/2 -  2 pt)"},{"e":2305,"s":95,"a":76,"b":108,"w":0.0,"p":4,"d":"DORSEY, TYLER (TEL) \u2014 Two Pointer (3/5 -  12 pt)"},{"e":2316,"s":84,"a":79,"b":108,"w":0.0,"p":4,"d":"SHENGELIA, TORNIKE (BAS) \u2014 Three Pointer (6/8 -  31 pt)"},{"e":2343,"s":57,"a":81,"b":108,"w":0.0,"p":4,"d":"VILDOZA, LUCA (BAS) \u2014 Two Pointer (1/4 -  4 pt)"},{"e":2364,"s":36,"a":81,"b":110,"w":0.0,"p":4,"d":"COHEN, JAKE (TEL) \u2014 Two Pointer (2/3 -  4 pt)"},{"e":2364,"s":36,"a":81,"b":111,"w":0.0,"p":4,"d":"COHEN, JAKE (TEL) \u2014 Free Throw In (1/1 -  5 pt)"},{"e":2370,"s":30,"a":82,"b":111,"w":0.0,"p":4,"d":"VILDOZA, LUCA (BAS) \u2014 Free Throw In (3/3 -  5 pt)"},{"e":2370,"s":30,"a":83,"b":111,"w":0.0,"p":4,"d":"VILDOZA, LUCA (BAS) \u2014 Free Throw In (4/4 -  6 pt)"},{"e":2386,"s":14,"a":83,"b":113,"w":0.0,"p":4,"d":"ACY, QUINCY (TEL) \u2014 Two Pointer (2/3 -  7 pt)"},{"e":2400,"s":0,"a":83,"b":113,"w":0.0,"p":4,"d":"Final Buzzer"}]}