{"ta":"DAR","tb":"ZAL","timeline":[{"e":45,"s":2355,"a":2,"b":2,"w":0.5,"p":1,"d":"ULANOVAS, EDGARAS (ZAL) \u2014 Two Pointer (1/1 -  2 pt)"},{"e":83,"s":2317,"a":2,"b":4,"w":0.4631,"p":1,"d":"DAVIES, BRANDON (ZAL) \u2014 Two Pointer (1/1 -  2 pt)"},{"e":83,"s":2317,"a":2,"b":5,"w":0.4447,"p":1,"d":"DAVIES, BRANDON (ZAL) \u2014 Free Throw In (1/1 -  3 pt)"},{"e":97,"s":2303,"a":5,"b":5,"w":0.5,"p":1,"d":"BROWN, MARKEL (DAR) \u2014 Three Pointer (1/1 -  3 pt)"},{"e":124,"s":2276,"a":5,"b":8,"w":0.4442,"p":1,"d":"GRIGONIS, MARIUS (ZAL) \u2014 Three Pointer (1/1 -  3 pt)"},{"e":168,"s":2232,"a":8,"b":8,"w":0.5,"p":1,"d":"BROWN, MARKEL (DAR) \u2014 Three Pointer (2/2 -  6 pt)"},{"e":221,"s":2179,"a":8,"b":9,"w":0.4809,"p":1,"d":"GRIGONIS, MARIUS (ZAL) \u2014 Free Throw In (1/2 -  4 pt)"},{"e":304,"s":2096,"a":10,"b":9,"w":0.5194,"p":1,"d":"KIDD, STANTON (DAR) \u2014 Two Pointer (1/2 -  2 pt)"},{"e":363,"s":2037,"a":10,"b":11,"w":0.4803,"p":1,"d":"WHITE, AARON (ZAL) \u2014 Two Pointer (1/1 -  2 pt)"},{"e":401,"s":1999,"a":12,"b":11,"w":0.5199,"p":1,"d":"ERIC, MICHAEL (DAR) \u2014 Two Pointer (2/2 -  4 pt)"},{"e":401,"s":1999,"a":13,"b":11,"w":0.5398,"p":1,"d":"ERIC, MICHAEL (DAR) \u2014 Free Throw In (1/1 -  5 pt)"},{"e":453,"s":1947,"a":13,"b":13,"w":0.5,"p":1,"d":"JOKUBAITIS, ROKAS (ZAL) \u2014 Two Pointer (1/2 -  2 pt)"},{"e":500,"s":1900,"a":15,"b":13,"w":0.5408,"p":1,"d":"ERIC, MICHAEL (DAR) \u2014 Two Pointer (3/3 -  7 pt)"},{"e":521,"s":1879,"a":17,"b":13,"w":0.5815,"p":1,"d":"DOUGLAS, TONEY (DAR) \u2014 Two Pointer (1/1 -  2 pt)"},{"e":539,"s":1861,"a":17,"b":14,"w":0.5616,"p":1,"d":"MILAKNIS, ARTURAS (ZAL) \u2014 Free Throw In (1/1 -  1 pt)"},{"e":539,"s":1861,"a":17,"b":15,"w":0.5412,"p":1,"d":"MILAKNIS, ARTURAS (ZAL) \u2014 Free Throw In (2/2 -  2 pt)"},{"e":560,"s":1840,"a":18,"b":15,"w":0.562,"p":1,"d":"SAVAS, OGUZ (DAR) \u2014 Free Throw In (1/1 -  1 pt)"},{"e":560,"s":1840,"a":19,"b":15,"w":0.5823,"p":1,"d":"SAVAS, OGUZ (DAR) \u2014 Free Throw In (2/2 -  2 pt)"},{"e":605,"s":1795,"a":21,"b":15,"w":0.6235,"p":2,"d":"OZDEMIROGLU, DOGUS (DAR) \u2014 Two Pointer (1/3 -  2 pt)"},{"e":673,"s":1727,"a":23,"b":15,"w":0.665,"p":2,"d":"SAVAS, OGUZ (DAR) \u2014 Two Pointer (1/1 -  4 pt)"},{"e":722,"s":1678,"a":23,"b":16,"w":0.6477,"p":2,"d":"DAVIES, BRANDON (ZAL) \u2014 Free Throw In (2/2 -  4 pt)"},{"e":722,"s":1678,"a":23,"b":17,"w":0.6276,"p":2,"d":"DAVIES, BRANDON (ZAL) \u2014 Free Throw In (3/3 -  5 pt)"},{"e":785,"s":1615,"a":23,"b":19,"w":0.5877,"p":2,"d":"DAVIES, BRANDON (ZAL) \u2014 Two Pointer (2/4 -  7 pt)"},{"e":818,"s":1582,"a":23,"b":21,"w":0.5447,"p":2,"d":"DAVIES, BRANDON (ZAL) \u2014 Two Pointer (3/5 -  9 pt)"},{"e":843,"s":1557,"a":26,"b":21,"w":0.611,"p":2,"d":"MCCALLUM, RAY (DAR) \u2014 Three Pointer (1/1 -  3 pt)"},{"e":878,"s":1522,"a":26,"b":22,"w":0.5903,"p":2,"d":"DAVIES, BRANDON (ZAL) \u2014 Free Throw In (4/4 -  10 pt)"},{"e":878,"s":1522,"a":26,"b":23,"w":0.5681,"p":2,"d":"DAVIES, BRANDON (ZAL) \u2014 Free Throw In (5/5 -  11 pt)"},{"e":900,"s":1500,"a":26,"b":25,"w":0.523,"p":2,"d":"WALTON JR, DERRICK (ZAL) \u2014 Two Pointer (1/2 -  2 pt)"},{"e":928,"s":1472,"a":26,"b":26,"w":0.5,"p":2,"d":"ULANOVAS, EDGARAS (ZAL) \u2014 Free Throw In (1/1 -  3 pt)"},{"e":928,"s":1472,"a":26,"b":27,"w":0.4768,"p":2,"d":"ULANOVAS, EDGARAS (ZAL) \u2014 Free Throw In (2/2 -  4 pt)"},{"e":946,"s":1454,"a":28,"b":27,"w":0.5233,"p":2,"d":"DOUGLAS, TONEY (DAR) \u2014 Two Pointer (2/2 -  4 pt)"},{"e":1025,"s":1375,"a":28,"b":29,"w":0.476,"p":2,"d":"WESTERMANN, LEO (ZAL) \u2014 Two Pointer (1/2 -  2 pt)"},{"e":1041,"s":1359,"a":31,"b":29,"w":0.5482,"p":2,"d":"DIEBLER, JON (DAR) \u2014 Three Pointer (1/3 -  3 pt)"},{"e":1059,"s":1341,"a":31,"b":30,"w":0.5243,"p":2,"d":"WESTERMANN, LEO (ZAL) \u2014 Free Throw In (1/1 -  3 pt)"},{"e":1059,"s":1341,"a":31,"b":31,"w":0.5,"p":2,"d":"WESTERMANN, LEO (ZAL) \u2014 Free Throw In (2/2 -  4 pt)"},{"e":1066,"s":1334,"a":32,"b":31,"w":0.5244,"p":2,"d":"DIEBLER, JON (DAR) \u2014 Free Throw In (1/1 -  4 pt)"},{"e":1066,"s":1334,"a":33,"b":31,"w":0.5486,"p":2,"d":"DIEBLER, JON (DAR) \u2014 Free Throw In (2/2 -  5 pt)"},{"e":1066,"s":1334,"a":34,"b":31,"w":0.5726,"p":2,"d":"DIEBLER, JON (DAR) \u2014 Free Throw In (3/3 -  6 pt)"},{"e":1112,"s":1288,"a":37,"b":31,"w":0.6447,"p":2,"d":"DIEBLER, JON (DAR) \u2014 Three Pointer (2/4 -  9 pt)"},{"e":1124,"s":1276,"a":37,"b":32,"w":0.6222,"p":2,"d":"MILAKNIS, ARTURAS (ZAL) \u2014 Free Throw In (3/4 -  3 pt)"},{"e":1190,"s":1210,"a":39,"b":32,"w":0.6719,"p":2,"d":"EVANS, JEREMY (DAR) \u2014 Two Pointer (1/1 -  2 pt)"},{"e":1196,"s":1204,"a":39,"b":33,"w":0.6493,"p":2,"d":"WESTERMANN, LEO (ZAL) \u2014 Free Throw In (3/3 -  5 pt)"},{"e":1247,"s":1153,"a":39,"b":35,"w":0.6034,"p":3,"d":"DAVIES, BRANDON (ZAL) \u2014 Two Pointer (4/8 -  13 pt)"},{"e":1317,"s":1083,"a":39,"b":37,"w":0.5539,"p":3,"d":"WALTON JR, DERRICK (ZAL) \u2014 Two Pointer (2/4 -  4 pt)"},{"e":1336,"s":1064,"a":42,"b":37,"w":0.6332,"p":3,"d":"MCCALLUM, RAY (DAR) \u2014 Three Pointer (2/3 -  6 pt)"},{"e":1382,"s":1018,"a":42,"b":38,"w":0.6098,"p":3,"d":"WHITE, AARON (ZAL) \u2014 Free Throw In (1/2 -  3 pt)"},{"e":1401,"s":999,"a":45,"b":38,"w":0.6876,"p":3,"d":"DIEBLER, JON (DAR) \u2014 Three Pointer (3/6 -  12 pt)"},{"e":1499,"s":901,"a":45,"b":40,"w":0.6442,"p":3,"d":"DAVIES, BRANDON (ZAL) \u2014 Two Pointer (5/9 -  15 pt)"},{"e":1511,"s":889,"a":48,"b":40,"w":0.7223,"p":3,"d":"MCCALLUM, RAY (DAR) \u2014 Three Pointer (3/4 -  9 pt)"},{"e":1567,"s":833,"a":48,"b":42,"w":0.6771,"p":3,"d":"WESTERMANN, LEO (ZAL) \u2014 Two Pointer (2/4 -  7 pt)"},{"e":1609,"s":791,"a":48,"b":45,"w":0.5939,"p":3,"d":"GRIGONIS, MARIUS (ZAL) \u2014 Three Pointer (2/3 -  7 pt)"},{"e":1628,"s":772,"a":50,"b":45,"w":0.655,"p":3,"d":"ERIC, MICHAEL (DAR) \u2014 Two Pointer (4/6 -  9 pt)"},{"e":1676,"s":724,"a":52,"b":45,"w":0.7164,"p":3,"d":"PEINERS, ZANIS (DAR) \u2014 Two Pointer (1/1 -  2 pt)"},{"e":1699,"s":701,"a":52,"b":46,"w":0.6916,"p":3,"d":"GRIGONIS, MARIUS (ZAL) \u2014 Free Throw In (2/3 -  8 pt)"},{"e":1699,"s":701,"a":52,"b":47,"w":0.6621,"p":3,"d":"GRIGONIS, MARIUS (ZAL) \u2014 Free Throw In (3/4 -  9 pt)"},{"e":1740,"s":660,"a":53,"b":47,"w":0.6968,"p":3,"d":"MCCALLUM, RAY (DAR) \u2014 Free Throw In (1/1 -  10 pt)"},{"e":1754,"s":646,"a":53,"b":48,"w":0.6684,"p":3,"d":"DAVIES, BRANDON (ZAL) \u2014 Free Throw In (6/6 -  16 pt)"},{"e":1754,"s":646,"a":53,"b":49,"w":0.6366,"p":3,"d":"DAVIES, BRANDON (ZAL) \u2014 Free Throw In (7/7 -  17 pt)"},{"e":1826,"s":574,"a":53,"b":50,"w":0.6097,"p":4,"d":"GRIGONIS, MARIUS (ZAL) \u2014 Free Throw In (4/5 -  10 pt)"},{"e":1869,"s":531,"a":53,"b":52,"w":0.5386,"p":4,"d":"WALKUP, THOMAS (ZAL) \u2014 Two Pointer (1/2 -  2 pt)"},{"e":1903,"s":497,"a":53,"b":54,"w":0.4601,"p":4,"d":"WALKUP, THOMAS (ZAL) \u2014 Two Pointer (2/3 -  4 pt)"},{"e":1936,"s":464,"a":54,"b":54,"w":0.5,"p":4,"d":"BROWN, MARKEL (DAR) \u2014 Free Throw In (1/1 -  7 pt)"},{"e":1936,"s":464,"a":55,"b":54,"w":0.5413,"p":4,"d":"BROWN, MARKEL (DAR) \u2014 Free Throw In (2/2 -  8 pt)"},{"e":1959,"s":441,"a":55,"b":56,"w":0.4577,"p":4,"d":"WALKUP, THOMAS (ZAL) \u2014 Two Pointer (3/4 -  6 pt)"},{"e":1984,"s":416,"a":56,"b":56,"w":0.5,"p":4,"d":"KIDD, STANTON (DAR) \u2014 Free Throw In (1/1 -  3 pt)"},{"e":1984,"s":416,"a":57,"b":56,"w":0.5436,"p":4,"d":"KIDD, STANTON (DAR) \u2014 Free Throw In (2/3 -  4 pt)"},{"e":2025,"s":375,"a":59,"b":56,"w":0.6346,"p":4,"d":"MCCALLUM, RAY (DAR) \u2014 Two Pointer (1/5 -  12 pt)"},{"e":2062,"s":338,"a":59,"b":59,"w":0.5,"p":4,"d":"MILAKNIS, ARTURAS (ZAL) \u2014 Three Pointer (1/2 -  6 pt)"},{"e":2090,"s":310,"a":61,"b":59,"w":0.5998,"p":4,"d":"EVANS, JEREMY (DAR) \u2014 Two Pointer (2/2 -  4 pt)"},{"e":2148,"s":252,"a":61,"b":60,"w":0.5559,"p":4,"d":"WHITE, AARON (ZAL) \u2014 Free Throw In (2/3 -  4 pt)"},{"e":2148,"s":252,"a":61,"b":61,"w":0.5,"p":4,"d":"WHITE, AARON (ZAL) \u2014 Free Throw In (3/4 -  5 pt)"},{"e":2158,"s":242,"a":63,"b":61,"w":0.6126,"p":4,"d":"EVANS, JEREMY (DAR) \u2014 Two Pointer (3/3 -  6 pt)"},{"e":2200,"s":200,"a":66,"b":61,"w":0.779,"p":4,"d":"BROWN, MARKEL (DAR) \u2014 Three Pointer (3/5 -  11 pt)"},{"e":2209,"s":191,"a":66,"b":62,"w":0.7372,"p":4,"d":"ULANOVAS, EDGARAS (ZAL) \u2014 Free Throw In (3/3 -  5 pt)"},{"e":2209,"s":191,"a":66,"b":63,"w":0.6843,"p":4,"d":"ULANOVAS, EDGARAS (ZAL) \u2014 Free Throw In (4/4 -  6 pt)"},{"e":2272,"s":128,"a":66,"b":64,"w":0.6525,"p":4,"d":"MILAKNIS, ARTURAS (ZAL) \u2014 Free Throw In (4/5 -  7 pt)"},{"e":2272,"s":128,"a":66,"b":65,"w":0.5781,"p":4,"d":"MILAKNIS, ARTURAS (ZAL) \u2014 Free Throw In (5/6 -  8 pt)"},{"e":2290,"s":110,"a":69,"b":65,"w":0.7956,"p":4,"d":"MCCALLUM, RAY (DAR) \u2014 Three Pointer (4/8 -  15 pt)"},{"e":2306,"s":94,"a":69,"b":68,"w":0.5909,"p":4,"d":"WHITE, AARON (ZAL) \u2014 Three Pointer (1/2 -  8 pt)"},{"e":2326,"s":74,"a":71,"b":68,"w":0.776,"p":4,"d":"MCCALLUM, RAY (DAR) \u2014 Two Pointer (2/8 -  17 pt)"},{"e":2342,"s":58,"a":71,"b":70,"w":0.6149,"p":4,"d":"WHITE, AARON (ZAL) \u2014 Two Pointer (2/2 -  10 pt)"},{"e":2374,"s":26,"a":71,"b":73,"w":0.1982,"p":4,"d":"WESTERMANN, LEO (ZAL) \u2014 Three Pointer (1/3 -  10 pt)"},{"e":2394,"s":6,"a":71,"b":74,"w":0.0126,"p":4,"d":"WESTERMANN, LEO (ZAL) \u2014 Free Throw In (4/4 -  11 pt)"},{"e":2394,"s":6,"a":71,"b":75,"w":0.003,"p":4,"d":"WESTERMANN, LEO (ZAL) \u2014 Free Throw In (5/5 -  12 pt)"},{"e":2400,"s":0,"a":71,"b":75,"w":0.0,"p":4,"d":"Final Buzzer"}]}