[
    {
        "LocalTeam": "ZAL",
        "RoadTeam": "OLY"
    },
    {
        "LocalTeam": "DUB",
        "RoadTeam": "ASV"
    },
    {
        "LocalTeam": "ULK",
        "RoadTeam": "PAR"
    },
    {
        "LocalTeam": "VIR",
        "RoadTeam": "BAR"
    },
    {
        "LocalTeam": "MCO",
        "RoadTeam": "TEL"
    },
    {
        "LocalTeam": "PAN",
        "RoadTeam": "PRS"
    },
    {
        "LocalTeam": "RED",
        "RoadTeam": "IST"
    },
    {
        "LocalTeam": "BAS",
        "RoadTeam": "PAM"
    },
    {
        "LocalTeam": "MAD",
        "RoadTeam": "MUN"
    },
    {
        "LocalTeam": "HTA",
        "RoadTeam": "MIL"
    }
]