{"ta":"TEL","tb":"PRS","timeline":[{"e":55,"s":2345,"a":3,"b":2,"w":0.5184,"p":1,"d":"OUATTARA, YAKUBA (PRS) \u2014 Two Pointer (1/1 -  2 pt)"},{"e":65,"s":2335,"a":5,"b":2,"w":0.5551,"p":1,"d":"HOARD, JAYLEN (TEL) \u2014 Two Pointer (1/1 -  2 pt)"},{"e":82,"s":2318,"a":7,"b":2,"w":0.5915,"p":1,"d":"HOARD, JAYLEN (TEL) \u2014 Two Pointer (2/2 -  4 pt)"},{"e":157,"s":2243,"a":9,"b":2,"w":0.6287,"p":1,"d":"LEAF, TJ (TEL) \u2014 Two Pointer (1/1 -  2 pt)"},{"e":211,"s":2189,"a":9,"b":4,"w":0.5941,"p":1,"d":"AYAYI, JOEL (PRS) \u2014 Two Pointer (1/1 -  2 pt)"},{"e":254,"s":2146,"a":9,"b":7,"w":0.5384,"p":1,"d":"WILLIS, DEREK (PRS) \u2014 Three Pointer (1/2 -  3 pt)"},{"e":275,"s":2125,"a":9,"b":9,"w":0.5,"p":1,"d":"WILLIS, DEREK (PRS) \u2014 Two Pointer (1/2 -  5 pt)"},{"e":294,"s":2106,"a":10,"b":9,"w":0.5194,"p":1,"d":"LEAF, TJ (TEL) \u2014 Free Throw In (1/1 -  3 pt)"},{"e":294,"s":2106,"a":11,"b":9,"w":0.5387,"p":1,"d":"LEAF, TJ (TEL) \u2014 Free Throw In (2/2 -  4 pt)"},{"e":329,"s":2071,"a":11,"b":12,"w":0.4804,"p":1,"d":"HIFI, NADIR (PRS) \u2014 Three Pointer (1/2 -  3 pt)"},{"e":351,"s":2049,"a":11,"b":15,"w":0.4219,"p":1,"d":"HIFI, NADIR (PRS) \u2014 Three Pointer (2/4 -  6 pt)"},{"e":393,"s":2007,"a":11,"b":17,"w":0.3829,"p":1,"d":"HERRERA, SEBASTIAN (PRS) \u2014 Two Pointer (1/1 -  2 pt)"},{"e":423,"s":1977,"a":11,"b":19,"w":0.345,"p":1,"d":"ROBINSON, JUSTIN (PRS) \u2014 Two Pointer (1/2 -  2 pt)"},{"e":436,"s":1964,"a":14,"b":19,"w":0.4008,"p":1,"d":"BLATT, TAMIR (TEL) \u2014 Three Pointer (1/1 -  3 pt)"},{"e":446,"s":1954,"a":14,"b":21,"w":0.3626,"p":1,"d":"OUATTARA, YAKUBA (PRS) \u2014 Two Pointer (2/2 -  4 pt)"},{"e":485,"s":1915,"a":14,"b":23,"w":0.3246,"p":1,"d":"BAKO, ISMAEL (PRS) \u2014 Two Pointer (1/1 -  2 pt)"},{"e":502,"s":1898,"a":16,"b":23,"w":0.3607,"p":1,"d":"SORKIN, ROMAN (TEL) \u2014 Two Pointer (1/2 -  2 pt)"},{"e":511,"s":1889,"a":16,"b":24,"w":0.3417,"p":1,"d":"ROBINSON, JUSTIN (PRS) \u2014 Free Throw In (1/1 -  3 pt)"},{"e":511,"s":1889,"a":16,"b":25,"w":0.3235,"p":1,"d":"ROBINSON, JUSTIN (PRS) \u2014 Free Throw In (2/2 -  4 pt)"},{"e":524,"s":1876,"a":19,"b":25,"w":0.3791,"p":1,"d":"WALKER IV, LONNIE (TEL) \u2014 Three Pointer (1/1 -  3 pt)"},{"e":555,"s":1845,"a":20,"b":25,"w":0.3978,"p":1,"d":"SANTOS, MARCIO (TEL) \u2014 Free Throw In (1/2 -  1 pt)"},{"e":572,"s":1828,"a":20,"b":27,"w":0.3582,"p":1,"d":"DOKOSSI, ALLAN (PRS) \u2014 Two Pointer (1/2 -  2 pt)"},{"e":644,"s":1756,"a":21,"b":27,"w":0.3752,"p":2,"d":"WALKER IV, LONNIE (TEL) \u2014 Free Throw In (1/1 -  4 pt)"},{"e":644,"s":1756,"a":22,"b":27,"w":0.3953,"p":2,"d":"WALKER IV, LONNIE (TEL) \u2014 Free Throw In (2/2 -  5 pt)"},{"e":644,"s":1756,"a":23,"b":27,"w":0.4158,"p":2,"d":"WALKER IV, LONNIE (TEL) \u2014 Free Throw In (3/3 -  6 pt)"},{"e":669,"s":1731,"a":23,"b":29,"w":0.3743,"p":2,"d":"ROBINSON, JUSTIN (PRS) \u2014 Two Pointer (2/5 -  6 pt)"},{"e":724,"s":1676,"a":24,"b":29,"w":0.3929,"p":2,"d":"WALKER IV, LONNIE (TEL) \u2014 Free Throw In (4/4 -  7 pt)"},{"e":724,"s":1676,"a":25,"b":29,"w":0.4138,"p":2,"d":"WALKER IV, LONNIE (TEL) \u2014 Free Throw In (5/5 -  8 pt)"},{"e":750,"s":1650,"a":25,"b":31,"w":0.3714,"p":2,"d":"FAYE, MOUHAMED (PRS) \u2014 Two Pointer (1/1 -  2 pt)"},{"e":758,"s":1642,"a":26,"b":31,"w":0.3918,"p":2,"d":"HOARD, JAYLEN (TEL) \u2014 Free Throw In (1/1 -  5 pt)"},{"e":758,"s":1642,"a":27,"b":31,"w":0.413,"p":2,"d":"HOARD, JAYLEN (TEL) \u2014 Free Throw In (2/2 -  6 pt)"},{"e":772,"s":1628,"a":27,"b":32,"w":0.3914,"p":2,"d":"WILLIS, DEREK (PRS) \u2014 Free Throw In (1/2 -  6 pt)"},{"e":824,"s":1576,"a":29,"b":32,"w":0.4331,"p":2,"d":"CLARK III, JIMMY (TEL) \u2014 Two Pointer (1/2 -  2 pt)"},{"e":830,"s":1570,"a":29,"b":33,"w":0.411,"p":2,"d":"MORGAN, JEREMY (PRS) \u2014 Free Throw In (1/2 -  1 pt)"},{"e":830,"s":1570,"a":29,"b":34,"w":0.3895,"p":2,"d":"MORGAN, JEREMY (PRS) \u2014 Free Throw In (2/3 -  2 pt)"},{"e":862,"s":1538,"a":29,"b":36,"w":0.3462,"p":2,"d":"DOKOSSI, ALLAN (PRS) \u2014 Two Pointer (2/3 -  4 pt)"},{"e":938,"s":1462,"a":29,"b":38,"w":0.3018,"p":2,"d":"ROBINSON, JUSTIN (PRS) \u2014 Two Pointer (3/7 -  8 pt)"},{"e":954,"s":1446,"a":32,"b":38,"w":0.363,"p":2,"d":"DOWTIN JR, JEFFREY (TEL) \u2014 Three Pointer (2/3 -  6 pt)"},{"e":992,"s":1408,"a":32,"b":40,"w":0.3187,"p":2,"d":"WILLIS, DEREK (PRS) \u2014 Two Pointer (2/3 -  8 pt)"},{"e":1018,"s":1382,"a":32,"b":42,"w":0.2772,"p":2,"d":"BAKO, ISMAEL (PRS) \u2014 Two Pointer (2/2 -  4 pt)"},{"e":1057,"s":1343,"a":35,"b":42,"w":0.3361,"p":2,"d":"WALKER IV, LONNIE (TEL) \u2014 Three Pointer (2/5 -  11 pt)"},{"e":1070,"s":1330,"a":35,"b":45,"w":0.2735,"p":2,"d":"MORGAN, JEREMY (PRS) \u2014 Three Pointer (1/2 -  5 pt)"},{"e":1105,"s":1295,"a":38,"b":45,"w":0.3334,"p":2,"d":"SANTOS, MARCIO (TEL) \u2014 Three Pointer (1/1 -  4 pt)"},{"e":1147,"s":1253,"a":41,"b":45,"w":0.4007,"p":2,"d":"DOWTIN JR, JEFFREY (TEL) \u2014 Three Pointer (3/4 -  9 pt)"},{"e":1159,"s":1241,"a":41,"b":48,"w":0.33,"p":2,"d":"HIFI, NADIR (PRS) \u2014 Three Pointer (3/7 -  9 pt)"},{"e":1218,"s":1182,"a":43,"b":48,"w":0.3733,"p":3,"d":"HOARD, JAYLEN (TEL) \u2014 Two Pointer (3/5 -  8 pt)"},{"e":1237,"s":1163,"a":43,"b":51,"w":0.3024,"p":3,"d":"ROBINSON, JUSTIN (PRS) \u2014 Three Pointer (1/3 -  11 pt)"},{"e":1256,"s":1144,"a":44,"b":51,"w":0.3236,"p":3,"d":"WALKER IV, LONNIE (TEL) \u2014 Free Throw In (6/6 -  12 pt)"},{"e":1371,"s":1029,"a":46,"b":51,"w":0.3646,"p":3,"d":"DOWTIN JR, JEFFREY (TEL) \u2014 Two Pointer (1/4 -  11 pt)"},{"e":1379,"s":1021,"a":46,"b":53,"w":0.3142,"p":3,"d":"HIFI, NADIR (PRS) \u2014 Two Pointer (1/2 -  11 pt)"},{"e":1443,"s":957,"a":46,"b":55,"w":0.2618,"p":3,"d":"DOKOSSI, ALLAN (PRS) \u2014 Two Pointer (3/4 -  6 pt)"},{"e":1452,"s":948,"a":47,"b":55,"w":0.2838,"p":3,"d":"HOARD, JAYLEN (TEL) \u2014 Free Throw In (3/3 -  9 pt)"},{"e":1452,"s":948,"a":48,"b":55,"w":0.3079,"p":3,"d":"HOARD, JAYLEN (TEL) \u2014 Free Throw In (4/4 -  10 pt)"},{"e":1481,"s":919,"a":48,"b":57,"w":0.2577,"p":3,"d":"HIFI, NADIR (PRS) \u2014 Two Pointer (2/3 -  13 pt)"},{"e":1490,"s":910,"a":50,"b":57,"w":0.3043,"p":3,"d":"WALKER IV, LONNIE (TEL) \u2014 Two Pointer (1/3 -  14 pt)"},{"e":1494,"s":906,"a":50,"b":58,"w":0.2795,"p":3,"d":"HIFI, NADIR (PRS) \u2014 Free Throw In (1/1 -  14 pt)"},{"e":1494,"s":906,"a":50,"b":59,"w":0.2563,"p":3,"d":"HIFI, NADIR (PRS) \u2014 Free Throw In (2/3 -  15 pt)"},{"e":1513,"s":887,"a":52,"b":59,"w":0.3021,"p":3,"d":"HOARD, JAYLEN (TEL) \u2014 Two Pointer (4/7 -  12 pt)"},{"e":1531,"s":869,"a":52,"b":61,"w":0.252,"p":3,"d":"ROBINSON, JUSTIN (PRS) \u2014 Two Pointer (4/9 -  13 pt)"},{"e":1547,"s":853,"a":54,"b":61,"w":0.2986,"p":3,"d":"BLATT, TAMIR (TEL) \u2014 Two Pointer (1/2 -  5 pt)"},{"e":1550,"s":850,"a":54,"b":62,"w":0.2734,"p":3,"d":"HERRERA, SEBASTIAN (PRS) \u2014 Free Throw In (1/1 -  3 pt)"},{"e":1556,"s":844,"a":54,"b":65,"w":0.206,"p":3,"d":"OUATTARA, YAKUBA (PRS) \u2014 Three Pointer (1/5 -  7 pt)"},{"e":1575,"s":825,"a":55,"b":65,"w":0.2244,"p":3,"d":"BRISSETT, O'SHAE J (TEL) \u2014 Free Throw In (1/1 -  1 pt)"},{"e":1575,"s":825,"a":56,"b":65,"w":0.2467,"p":3,"d":"BRISSETT, O'SHAE J (TEL) \u2014 Free Throw In (2/2 -  2 pt)"},{"e":1604,"s":796,"a":57,"b":65,"w":0.2669,"p":3,"d":"BRISSETT, O'SHAE J (TEL) \u2014 Free Throw In (3/3 -  3 pt)"},{"e":1620,"s":780,"a":57,"b":67,"w":0.2183,"p":3,"d":"ROBINSON, JUSTIN (PRS) \u2014 Two Pointer (5/10 -  15 pt)"},{"e":1666,"s":734,"a":59,"b":67,"w":0.2588,"p":3,"d":"BLATT, TAMIR (TEL) \u2014 Two Pointer (2/3 -  7 pt)"},{"e":1718,"s":682,"a":59,"b":68,"w":0.2266,"p":3,"d":"DOKOSSI, ALLAN (PRS) \u2014 Free Throw In (1/2 -  7 pt)"},{"e":1742,"s":658,"a":60,"b":68,"w":0.2477,"p":3,"d":"SANTOS, MARCIO (TEL) \u2014 Free Throw In (2/3 -  5 pt)"},{"e":1742,"s":658,"a":61,"b":68,"w":0.2744,"p":3,"d":"SANTOS, MARCIO (TEL) \u2014 Free Throw In (3/4 -  6 pt)"},{"e":1763,"s":637,"a":63,"b":68,"w":0.3305,"p":3,"d":"LEAF, TJ (TEL) \u2014 Two Pointer (2/3 -  6 pt)"},{"e":1776,"s":624,"a":63,"b":71,"w":0.2421,"p":3,"d":"AYAYI, JOEL (PRS) \u2014 Three Pointer (1/2 -  5 pt)"},{"e":1796,"s":604,"a":63,"b":74,"w":0.1687,"p":3,"d":"HIFI, NADIR (PRS) \u2014 Three Pointer (4/9 -  18 pt)"},{"e":1842,"s":558,"a":63,"b":76,"w":0.1234,"p":4,"d":"MORGAN, JEREMY (PRS) \u2014 Two Pointer (1/1 -  7 pt)"},{"e":1855,"s":545,"a":63,"b":77,"w":0.1056,"p":4,"d":"HIFI, NADIR (PRS) \u2014 Free Throw In (3/4 -  19 pt)"},{"e":1855,"s":545,"a":63,"b":78,"w":0.092,"p":4,"d":"HIFI, NADIR (PRS) \u2014 Free Throw In (4/5 -  20 pt)"},{"e":1855,"s":545,"a":63,"b":79,"w":0.08,"p":4,"d":"HIFI, NADIR (PRS) \u2014 Free Throw In (5/6 -  21 pt)"},{"e":1891,"s":509,"a":63,"b":80,"w":0.0639,"p":4,"d":"M'BAYE, AMATH (PRS) \u2014 Free Throw In (1/2 -  1 pt)"},{"e":1919,"s":481,"a":63,"b":83,"w":0.0374,"p":4,"d":"OUATTARA, YAKUBA (PRS) \u2014 Three Pointer (2/7 -  10 pt)"},{"e":1949,"s":451,"a":66,"b":83,"w":0.0546,"p":4,"d":"HOARD, JAYLEN (TEL) \u2014 Three Pointer (1/3 -  15 pt)"},{"e":1960,"s":440,"a":66,"b":85,"w":0.0382,"p":4,"d":"MORGAN, JEREMY (PRS) \u2014 Two Pointer (2/2 -  9 pt)"},{"e":1977,"s":423,"a":69,"b":85,"w":0.0589,"p":4,"d":"CLARK III, JIMMY (TEL) \u2014 Three Pointer (1/4 -  5 pt)"},{"e":2004,"s":396,"a":69,"b":87,"w":0.0383,"p":4,"d":"M'BAYE, AMATH (PRS) \u2014 Two Pointer (1/1 -  3 pt)"},{"e":2013,"s":387,"a":71,"b":87,"w":0.0523,"p":4,"d":"LEAF, TJ (TEL) \u2014 Two Pointer (3/5 -  8 pt)"},{"e":2071,"s":329,"a":71,"b":89,"w":0.0283,"p":4,"d":"HERRERA, SEBASTIAN (PRS) \u2014 Two Pointer (2/2 -  5 pt)"},{"e":2081,"s":319,"a":72,"b":89,"w":0.0326,"p":4,"d":"DOWTIN JR, JEFFREY (TEL) \u2014 Free Throw In (1/3 -  12 pt)"},{"e":2081,"s":319,"a":73,"b":89,"w":0.0395,"p":4,"d":"DOWTIN JR, JEFFREY (TEL) \u2014 Free Throw In (2/4 -  13 pt)"},{"e":2107,"s":293,"a":75,"b":89,"w":0.0515,"p":4,"d":"LEAF, TJ (TEL) \u2014 Two Pointer (4/7 -  10 pt)"},{"e":2140,"s":260,"a":75,"b":90,"w":0.0351,"p":4,"d":"HERRERA, SEBASTIAN (PRS) \u2014 Free Throw In (2/2 -  6 pt)"},{"e":2150,"s":250,"a":77,"b":90,"w":0.0507,"p":4,"d":"LEAF, TJ (TEL) \u2014 Two Pointer (5/8 -  12 pt)"},{"e":2178,"s":222,"a":78,"b":90,"w":0.0537,"p":4,"d":"WALKER IV, LONNIE (TEL) \u2014 Free Throw In (7/8 -  15 pt)"},{"e":2178,"s":222,"a":79,"b":90,"w":0.0672,"p":4,"d":"WALKER IV, LONNIE (TEL) \u2014 Free Throw In (8/9 -  16 pt)"},{"e":2237,"s":163,"a":81,"b":90,"w":0.075,"p":4,"d":"LEAF, TJ (TEL) \u2014 Two Pointer (6/9 -  14 pt)"},{"e":2255,"s":145,"a":81,"b":91,"w":0.0493,"p":4,"d":"OUATTARA, YAKUBA (PRS) \u2014 Free Throw In (1/1 -  11 pt)"},{"e":2255,"s":145,"a":81,"b":92,"w":0.0372,"p":4,"d":"OUATTARA, YAKUBA (PRS) \u2014 Free Throw In (2/2 -  12 pt)"},{"e":2279,"s":121,"a":82,"b":92,"w":0.0377,"p":4,"d":"SANTOS, MARCIO (TEL) \u2014 Free Throw In (4/5 -  7 pt)"},{"e":2279,"s":121,"a":83,"b":92,"w":0.0514,"p":4,"d":"SANTOS, MARCIO (TEL) \u2014 Free Throw In (5/6 -  8 pt)"},{"e":2295,"s":105,"a":83,"b":94,"w":0.0214,"p":4,"d":"DOKOSSI, ALLAN (PRS) \u2014 Two Pointer (4/5 -  9 pt)"},{"e":2315,"s":85,"a":83,"b":95,"w":0.0096,"p":4,"d":"M'BAYE, AMATH (PRS) \u2014 Free Throw In (2/4 -  4 pt)"},{"e":2326,"s":74,"a":85,"b":95,"w":0.0156,"p":4,"d":"RAYMAN, WILLIAM (TEL) \u2014 Two Pointer (1/1 -  2 pt)"},{"e":2342,"s":58,"a":85,"b":96,"w":0.0058,"p":4,"d":"M'BAYE, AMATH (PRS) \u2014 Free Throw In (3/5 -  5 pt)"},{"e":2342,"s":58,"a":85,"b":97,"w":0.0036,"p":4,"d":"M'BAYE, AMATH (PRS) \u2014 Free Throw In (4/6 -  6 pt)"},{"e":2363,"s":37,"a":85,"b":98,"w":0.0005,"p":4,"d":"HERRERA, SEBASTIAN (PRS) \u2014 Free Throw In (3/4 -  7 pt)"},{"e":2363,"s":37,"a":85,"b":99,"w":0.0003,"p":4,"d":"HERRERA, SEBASTIAN (PRS) \u2014 Free Throw In (4/5 -  8 pt)"},{"e":2372,"s":28,"a":88,"b":99,"w":0.0006,"p":4,"d":"CLARK III, JIMMY (TEL) \u2014 Three Pointer (2/6 -  8 pt)"},{"e":2378,"s":22,"a":88,"b":100,"w":0.0001,"p":4,"d":"M'BAYE, AMATH (PRS) \u2014 Free Throw In (5/7 -  7 pt)"},{"e":2378,"s":22,"a":88,"b":101,"w":0.0001,"p":4,"d":"M'BAYE, AMATH (PRS) \u2014 Free Throw In (6/8 -  8 pt)"},{"e":2393,"s":7,"a":91,"b":101,"w":0.0,"p":4,"d":"CLARK III, JIMMY (TEL) \u2014 Three Pointer (3/7 -  11 pt)"},{"e":2400,"s":0,"a":94,"b":101,"w":0.0,"p":4,"d":"DOWTIN JR, JEFFREY (TEL) \u2014 Three Pointer (4/5 -  16 pt)"},{"e":2400,"s":0,"a":94,"b":101,"w":0.0,"p":4,"d":"Final Buzzer"}]}