{"ta":"CSK","tb":"PAN","timeline":[{"e":63,"s":2337,"a":2,"b":2,"w":0.5,"p":1,"d":"KAUN, SASHA (CSK) \u2014 Layup Made (1/1 -  2 pt)"},{"e":163,"s":2237,"a":2,"b":4,"w":0.4624,"p":1,"d":"CHARALAMPOPOULOS, VASILIS (PAN) \u2014 Layup Made (2/2 -  4 pt)"},{"e":201,"s":2199,"a":4,"b":4,"w":0.5,"p":1,"d":"WEEMS, SONNY (CSK) \u2014 Layup Made (1/1 -  2 pt)"},{"e":268,"s":2132,"a":4,"b":6,"w":0.4615,"p":1,"d":"GIANKOVITS, VLANTIMIR (PAN) \u2014 Two Pointer (1/2 -  2 pt)"},{"e":279,"s":2121,"a":6,"b":6,"w":0.5,"p":1,"d":"TEODOSIC, MILOS (CSK) \u2014 Two Pointer (1/1 -  2 pt)"},{"e":296,"s":2104,"a":6,"b":8,"w":0.4612,"p":1,"d":"BATISTA, ESTEBAN (PAN) \u2014 Layup Made (1/2 -  2 pt)"},{"e":324,"s":2076,"a":8,"b":8,"w":0.5,"p":1,"d":"KAUN, SASHA (CSK) \u2014 Dunk (2/3 -  4 pt)"},{"e":337,"s":2063,"a":8,"b":11,"w":0.4414,"p":1,"d":"CHARALAMPOPOULOS, VASILIS (PAN) \u2014 Three Pointer (1/1 -  7 pt)"},{"e":378,"s":2022,"a":8,"b":14,"w":0.3833,"p":1,"d":"GIANKOVITS, VLANTIMIR (PAN) \u2014 Three Pointer (1/2 -  5 pt)"},{"e":398,"s":2002,"a":11,"b":14,"w":0.4406,"p":1,"d":"KIRILENKO, ANDREI (CSK) \u2014 Three Pointer (1/1 -  3 pt)"},{"e":439,"s":1961,"a":12,"b":14,"w":0.4599,"p":1,"d":"KAUN, SASHA (CSK) \u2014 Free Throw In (1/1 -  5 pt)"},{"e":487,"s":1913,"a":15,"b":14,"w":0.5204,"p":1,"d":"KIRILENKO, ANDREI (CSK) \u2014 Three Pointer (2/2 -  6 pt)"},{"e":535,"s":1865,"a":18,"b":14,"w":0.5818,"p":1,"d":"KIRILENKO, ANDREI (CSK) \u2014 Three Pointer (3/3 -  9 pt)"},{"e":540,"s":1860,"a":21,"b":14,"w":0.6407,"p":1,"d":"DE COLO, NANDO (CSK) \u2014 Three Pointer (1/1 -  3 pt)"},{"e":671,"s":1729,"a":23,"b":14,"w":0.6838,"p":2,"d":"DE COLO, NANDO (CSK) \u2014 Layup Made (1/1 -  5 pt)"},{"e":693,"s":1707,"a":23,"b":16,"w":0.6465,"p":2,"d":"PAPPAS, NIKOS (PAN) \u2014 Two Pointer (1/1 -  2 pt)"},{"e":714,"s":1686,"a":23,"b":18,"w":0.6068,"p":2,"d":"PAPPAS, NIKOS (PAN) \u2014 Layup Made (2/2 -  4 pt)"},{"e":732,"s":1668,"a":25,"b":18,"w":0.6481,"p":2,"d":"HINES, KYLE (CSK) \u2014 Layup Made (1/1 -  2 pt)"},{"e":753,"s":1647,"a":25,"b":19,"w":0.6287,"p":2,"d":"GIST, JAMES (PAN) \u2014 Free Throw In (1/1 -  1 pt)"},{"e":753,"s":1647,"a":25,"b":20,"w":0.608,"p":2,"d":"GIST, JAMES (PAN) \u2014 Free Throw In (2/2 -  2 pt)"},{"e":773,"s":1627,"a":27,"b":20,"w":0.6498,"p":2,"d":"DE COLO, NANDO (CSK) \u2014 Two Pointer (2/2 -  7 pt)"},{"e":815,"s":1585,"a":28,"b":20,"w":0.6717,"p":2,"d":"MARKOISHVILI, MANUCHAR (CSK) \u2014 Free Throw In (1/1 -  1 pt)"},{"e":815,"s":1585,"a":29,"b":20,"w":0.6911,"p":2,"d":"MARKOISHVILI, MANUCHAR (CSK) \u2014 Free Throw In (2/2 -  2 pt)"},{"e":832,"s":1568,"a":29,"b":23,"w":0.6318,"p":2,"d":"DIAMANTIDIS, DIMITRIS (PAN) \u2014 Three Pointer (1/2 -  3 pt)"},{"e":883,"s":1517,"a":29,"b":25,"w":0.5905,"p":2,"d":"BATISTA, ESTEBAN (PAN) \u2014 Layup Made (2/4 -  4 pt)"},{"e":904,"s":1496,"a":32,"b":25,"w":0.6558,"p":2,"d":"DE COLO, NANDO (CSK) \u2014 Three Pointer (2/3 -  10 pt)"},{"e":937,"s":1463,"a":34,"b":25,"w":0.6981,"p":2,"d":"NICHOLS, DEMETRIS (CSK) \u2014 Layup Made (1/1 -  2 pt)"},{"e":965,"s":1435,"a":34,"b":27,"w":0.6589,"p":2,"d":"BATISTA, ESTEBAN (PAN) \u2014 Layup Made (3/5 -  6 pt)"},{"e":985,"s":1415,"a":36,"b":27,"w":0.7011,"p":2,"d":"MARKOISHVILI, MANUCHAR (CSK) \u2014 Two Pointer (1/1 -  4 pt)"},{"e":1004,"s":1396,"a":36,"b":28,"w":0.682,"p":2,"d":"FOTSIS, ANTONIS (PAN) \u2014 Free Throw In (1/1 -  1 pt)"},{"e":1004,"s":1396,"a":36,"b":29,"w":0.6609,"p":2,"d":"FOTSIS, ANTONIS (PAN) \u2014 Free Throw In (2/2 -  2 pt)"},{"e":1018,"s":1382,"a":39,"b":29,"w":0.7228,"p":2,"d":"TEODOSIC, MILOS (CSK) \u2014 Three Pointer (1/3 -  5 pt)"},{"e":1037,"s":1363,"a":39,"b":31,"w":0.684,"p":2,"d":"BATISTA, ESTEBAN (PAN) \u2014 Layup Made (4/6 -  8 pt)"},{"e":1051,"s":1349,"a":40,"b":31,"w":0.7054,"p":2,"d":"NICHOLS, DEMETRIS (CSK) \u2014 Free Throw In (1/1 -  3 pt)"},{"e":1051,"s":1349,"a":41,"b":31,"w":0.7251,"p":2,"d":"NICHOLS, DEMETRIS (CSK) \u2014 Free Throw In (2/2 -  4 pt)"},{"e":1097,"s":1303,"a":41,"b":32,"w":0.7085,"p":2,"d":"BATISTA, ESTEBAN (PAN) \u2014 Free Throw In (1/1 -  9 pt)"},{"e":1097,"s":1303,"a":41,"b":33,"w":0.6878,"p":2,"d":"BATISTA, ESTEBAN (PAN) \u2014 Free Throw In (2/2 -  10 pt)"},{"e":1119,"s":1281,"a":43,"b":33,"w":0.7302,"p":2,"d":"KIRILENKO, ANDREI (CSK) \u2014 Layup Made (1/4 -  11 pt)"},{"e":1140,"s":1260,"a":47,"b":35,"w":0.7693,"p":2,"d":"DE COLO, NANDO (CSK) \u2014 Layup Made (3/3 -  12 pt)"},{"e":1144,"s":1256,"a":43,"b":35,"w":0.6909,"p":2,"d":"FOTSIS, ANTONIS (PAN) \u2014 Layup Made (1/1 -  4 pt)"},{"e":1163,"s":1237,"a":45,"b":35,"w":0.7336,"p":2,"d":"KIRILENKO, ANDREI (CSK) \u2014 Dunk (2/5 -  13 pt)"},{"e":1255,"s":1145,"a":47,"b":38,"w":0.7206,"p":3,"d":"GIANKOVITS, VLANTIMIR (PAN) \u2014 Three Pointer (2/4 -  8 pt)"},{"e":1270,"s":1130,"a":49,"b":38,"w":0.7624,"p":3,"d":"KAUN, SASHA (CSK) \u2014 Layup Made (3/5 -  7 pt)"},{"e":1299,"s":1101,"a":52,"b":38,"w":0.8181,"p":3,"d":"KIRILENKO, ANDREI (CSK) \u2014 Three Pointer (4/4 -  16 pt)"},{"e":1329,"s":1071,"a":52,"b":40,"w":0.7869,"p":3,"d":"CHARALAMPOPOULOS, VASILIS (PAN) \u2014 Layup Made (3/3 -  9 pt)"},{"e":1329,"s":1071,"a":54,"b":40,"w":0.8212,"p":3,"d":"KAUN, SASHA (CSK) \u2014 Dunk (4/6 -  9 pt)"},{"e":1428,"s":972,"a":56,"b":40,"w":0.8616,"p":3,"d":"DE COLO, NANDO (CSK) \u2014 Layup Made (4/4 -  14 pt)"},{"e":1450,"s":950,"a":56,"b":41,"w":0.8499,"p":3,"d":"GIST, JAMES (PAN) \u2014 Free Throw In (3/4 -  3 pt)"},{"e":1469,"s":931,"a":59,"b":41,"w":0.8911,"p":3,"d":"VORONTSEVICH, ANDREY (CSK) \u2014 Three Pointer (1/2 -  3 pt)"},{"e":1498,"s":902,"a":59,"b":44,"w":0.8556,"p":3,"d":"DIAMANTIDIS, DIMITRIS (PAN) \u2014 Three Pointer (2/3 -  6 pt)"},{"e":1520,"s":880,"a":59,"b":46,"w":0.8265,"p":3,"d":"MAVROKEFALIDIS, LOUKAS (PAN) \u2014 Layup Made (1/3 -  2 pt)"},{"e":1596,"s":804,"a":61,"b":46,"w":0.8682,"p":3,"d":"HINES, KYLE (CSK) \u2014 Dunk (2/2 -  4 pt)"},{"e":1614,"s":786,"a":61,"b":47,"w":0.8556,"p":3,"d":"CHARALAMPOPOULOS, VASILIS (PAN) \u2014 Free Throw In (1/1 -  10 pt)"},{"e":1614,"s":786,"a":61,"b":48,"w":0.8392,"p":3,"d":"CHARALAMPOPOULOS, VASILIS (PAN) \u2014 Free Throw In (2/2 -  11 pt)"},{"e":1665,"s":735,"a":64,"b":48,"w":0.8912,"p":3,"d":"WEEMS, SONNY (CSK) \u2014 Three Pointer (1/2 -  5 pt)"},{"e":1687,"s":713,"a":66,"b":48,"w":0.917,"p":3,"d":"JACKSON, AARON (CSK) \u2014 Layup Made (1/1 -  2 pt)"},{"e":1723,"s":677,"a":69,"b":48,"w":0.9466,"p":3,"d":"MARKOISHVILI, MANUCHAR (CSK) \u2014 Three Pointer (1/1 -  7 pt)"},{"e":1740,"s":660,"a":72,"b":54,"w":0.9239,"p":3,"d":"FOTSIS, ANTONIS (PAN) \u2014 Three Pointer (2/4 -  10 pt)"},{"e":1749,"s":651,"a":69,"b":51,"w":0.9251,"p":3,"d":"FOTSIS, ANTONIS (PAN) \u2014 Three Pointer (1/3 -  7 pt)"},{"e":1780,"s":620,"a":72,"b":51,"w":0.9528,"p":3,"d":"NICHOLS, DEMETRIS (CSK) \u2014 Three Pointer (1/1 -  7 pt)"},{"e":1810,"s":590,"a":74,"b":54,"w":0.9495,"p":4,"d":"JACKSON, AARON (CSK) \u2014 Layup Made (2/2 -  4 pt)"},{"e":1830,"s":570,"a":76,"b":54,"w":0.9638,"p":4,"d":"MARKOISHVILI, MANUCHAR (CSK) \u2014 Layup Made (2/3 -  9 pt)"},{"e":1848,"s":552,"a":78,"b":54,"w":0.9744,"p":4,"d":"WEEMS, SONNY (CSK) \u2014 Layup Made (2/3 -  7 pt)"},{"e":1849,"s":551,"a":79,"b":54,"w":0.978,"p":4,"d":"WEEMS, SONNY (CSK) \u2014 Free Throw In (1/1 -  8 pt)"},{"e":1874,"s":526,"a":79,"b":56,"w":0.9727,"p":4,"d":"GIANKOVITS, VLANTIMIR (PAN) \u2014 Two Pointer (2/4 -  10 pt)"},{"e":1888,"s":512,"a":82,"b":56,"w":0.9836,"p":4,"d":"WEEMS, SONNY (CSK) \u2014 Three Pointer (2/3 -  11 pt)"},{"e":1915,"s":485,"a":84,"b":56,"w":0.9893,"p":4,"d":"WEEMS, SONNY (CSK) \u2014 Dunk (3/4 -  13 pt)"},{"e":1937,"s":463,"a":84,"b":57,"w":0.9887,"p":4,"d":"GIST, JAMES (PAN) \u2014 Free Throw In (4/6 -  4 pt)"},{"e":1963,"s":437,"a":86,"b":57,"w":0.9929,"p":4,"d":"WEEMS, SONNY (CSK) \u2014 Layup Made (4/5 -  15 pt)"},{"e":1971,"s":429,"a":86,"b":59,"w":0.9905,"p":4,"d":"FOTSIS, ANTONIS (PAN) \u2014 Layup Made (2/2 -  12 pt)"},{"e":1993,"s":407,"a":86,"b":61,"w":0.9881,"p":4,"d":"GIST, JAMES (PAN) \u2014 Layup Made (1/4 -  6 pt)"},{"e":2011,"s":389,"a":86,"b":63,"w":0.9846,"p":4,"d":"GIST, JAMES (PAN) \u2014 Layup Made (2/5 -  8 pt)"},{"e":2011,"s":389,"a":86,"b":64,"w":0.9816,"p":4,"d":"GIST, JAMES (PAN) \u2014 Free Throw In (5/7 -  9 pt)"},{"e":2026,"s":374,"a":88,"b":64,"w":0.9881,"p":4,"d":"KOROBKOV, PAVEL (CSK) \u2014 Dunk (1/1 -  2 pt)"},{"e":2026,"s":374,"a":89,"b":64,"w":0.9901,"p":4,"d":"KOROBKOV, PAVEL (CSK) \u2014 Free Throw In (1/1 -  3 pt)"},{"e":2058,"s":342,"a":89,"b":66,"w":0.9882,"p":4,"d":"GIST, JAMES (PAN) \u2014 Dunk (3/6 -  11 pt)"},{"e":2082,"s":318,"a":91,"b":66,"w":0.9933,"p":4,"d":"WEEMS, SONNY (CSK) \u2014 Two Pointer (5/6 -  17 pt)"},{"e":2104,"s":296,"a":91,"b":68,"w":0.9915,"p":4,"d":"PAPPAS, NIKOS (PAN) \u2014 Layup Made (3/4 -  6 pt)"},{"e":2124,"s":276,"a":92,"b":68,"w":0.9942,"p":4,"d":"JACKSON, AARON (CSK) \u2014 Free Throw In (1/2 -  5 pt)"},{"e":2142,"s":258,"a":92,"b":70,"w":0.9925,"p":4,"d":"GIST, JAMES (PAN) \u2014 Dunk (4/7 -  13 pt)"},{"e":2172,"s":228,"a":92,"b":73,"w":0.9888,"p":4,"d":"PAPPAS, NIKOS (PAN) \u2014 Three Pointer (1/4 -  9 pt)"},{"e":2206,"s":194,"a":95,"b":73,"w":0.9964,"p":4,"d":"KHRYAPA, VICTOR (CSK) \u2014 Three Pointer (1/1 -  3 pt)"},{"e":2234,"s":166,"a":96,"b":73,"w":0.9983,"p":4,"d":"DE COLO, NANDO (CSK) \u2014 Free Throw In (1/1 -  15 pt)"},{"e":2234,"s":166,"a":97,"b":73,"w":0.9987,"p":4,"d":"DE COLO, NANDO (CSK) \u2014 Free Throw In (2/2 -  16 pt)"},{"e":2246,"s":154,"a":97,"b":75,"w":0.9982,"p":4,"d":"PAPPAS, NIKOS (PAN) \u2014 Layup Made (4/5 -  11 pt)"},{"e":2259,"s":141,"a":100,"b":75,"w":0.9994,"p":4,"d":"WEEMS, SONNY (CSK) \u2014 Three Pointer (3/5 -  20 pt)"},{"e":2278,"s":122,"a":100,"b":78,"w":0.9992,"p":4,"d":"CHARALAMPOPOULOS, VASILIS (PAN) \u2014 Three Pointer (2/2 -  14 pt)"},{"e":2340,"s":60,"a":100,"b":80,"w":0.9999,"p":4,"d":"PAPPAS, NIKOS (PAN) \u2014 Dunk (5/7 -  13 pt)"},{"e":2400,"s":0,"a":100,"b":80,"w":1.0,"p":4,"d":"Final Buzzer"}],"adv":{"q":[{"p":1,"a":21,"b":14},{"p":2,"a":26,"b":21},{"p":3,"a":25,"b":19},{"p":4,"a":28,"b":26}],"i":[{"n":"Batista","p":2,"h":6,"t":"PAN"},{"n":"Charalampopoulos","p":8,"h":5,"t":"PAN"},{"n":"De Colo","p":10,"h":5,"t":"CSK"},{"n":"Diamantidis","p":6,"h":7,"t":"PAN"},{"n":"Fotsis","p":8,"h":8,"t":"PAN"},{"n":"Giankovits","p":10,"h":6,"t":"PAN"},{"n":"Gist","p":5,"h":8,"t":"PAN"},{"n":"Hines","p":0,"h":3,"t":"CSK"},{"n":"Jackson","p":1,"h":4,"t":"CSK"},{"n":"Kaun","p":1,"h":4,"t":"CSK"},{"n":"Khryapa","p":3,"h":4,"t":"CSK"},{"n":"Kirilenko","p":12,"h":6,"t":"CSK"},{"n":"Korobkov","p":1,"h":1,"t":"CSK"},{"n":"Lountzis","p":0,"h":1,"t":"PAN"},{"n":"Markoishvili","p":7,"h":4,"t":"CSK"},{"n":"Mavrokefalidis","p":0,"h":2,"t":"PAN"},{"n":"Nelson","p":0,"h":1,"t":"PAN"},{"n":"Nichols","p":5,"h":6,"t":"CSK"},{"n":"Pappas","p":5,"h":4,"t":"PAN"},{"n":"Teodosic","p":5,"h":10,"t":"CSK"},{"n":"Vorontsevich","p":3,"h":7,"t":"CSK"},{"n":"Weems","p":12,"h":7,"t":"CSK"}]}}