{"ta":"BAR","tb":"LJU","timeline":[{"e":226,"s":2174,"a":11,"b":2,"w":0.6655,"p":1,"d":"GREEN, DANNY (LJU) \u2014 Two Pointer (1/4 -  2 pt)"},{"e":250,"s":2150,"a":11,"b":4,"w":0.6313,"p":1,"d":"GREEN, DANNY (LJU) \u2014 Two Pointer (2/5 -  4 pt)"},{"e":297,"s":2103,"a":12,"b":4,"w":0.6506,"p":1,"d":"PEROVIC, KOSTA (BAR) \u2014 Free Throw In (1/1 -  5 pt)"},{"e":297,"s":2103,"a":13,"b":4,"w":0.668,"p":1,"d":"PEROVIC, KOSTA (BAR) \u2014 Free Throw In (2/2 -  6 pt)"},{"e":315,"s":2085,"a":13,"b":6,"w":0.6333,"p":1,"d":"GREEN, DANNY (LJU) \u2014 Two Pointer (3/6 -  6 pt)"},{"e":341,"s":2059,"a":14,"b":6,"w":0.6521,"p":1,"d":"PEROVIC, KOSTA (BAR) \u2014 Free Throw In (3/3 -  7 pt)"},{"e":341,"s":2059,"a":15,"b":6,"w":0.6697,"p":1,"d":"PEROVIC, KOSTA (BAR) \u2014 Free Throw In (4/4 -  8 pt)"},{"e":363,"s":2037,"a":15,"b":8,"w":0.6347,"p":1,"d":"ROTHBART, BORIS (LJU) \u2014 Two Pointer (1/1 -  2 pt)"},{"e":378,"s":2022,"a":17,"b":8,"w":0.6711,"p":1,"d":"LORBEK, ERAZEM (BAR) \u2014 Two Pointer (1/1 -  2 pt)"},{"e":443,"s":1957,"a":19,"b":8,"w":0.708,"p":1,"d":"HUERTAS, MARCELINHO (BAR) \u2014 Two Pointer (2/2 -  4 pt)"},{"e":462,"s":1938,"a":19,"b":10,"w":0.6745,"p":1,"d":"GREEN, DANNY (LJU) \u2014 Two Pointer (4/8 -  8 pt)"},{"e":479,"s":1921,"a":21,"b":10,"w":0.7098,"p":1,"d":"NAVARRO, JUAN CARLOS (BAR) \u2014 Layup Made (2/3 -  7 pt)"},{"e":537,"s":1863,"a":21,"b":12,"w":0.6776,"p":1,"d":"SALIN, SASU (LJU) \u2014 Layup Made (1/1 -  2 pt)"},{"e":567,"s":1833,"a":21,"b":14,"w":0.6416,"p":1,"d":"CAPIN, ALEKSANDAR (LJU) \u2014 Dunk (1/1 -  2 pt)"},{"e":577,"s":1823,"a":23,"b":14,"w":0.6794,"p":1,"d":"MICKEAL, PETE (BAR) \u2014 Two Pointer (1/1 -  2 pt)"},{"e":596,"s":1804,"a":23,"b":15,"w":0.6617,"p":1,"d":"CAPIN, ALEKSANDAR (LJU) \u2014 Free Throw In (1/1 -  3 pt)"},{"e":596,"s":1804,"a":23,"b":16,"w":0.6427,"p":1,"d":"CAPIN, ALEKSANDAR (LJU) \u2014 Free Throw In (2/2 -  4 pt)"},{"e":668,"s":1732,"a":25,"b":16,"w":0.6836,"p":2,"d":"SADA, VICTOR (BAR) \u2014 Layup Made (1/1 -  2 pt)"},{"e":787,"s":1613,"a":27,"b":16,"w":0.7263,"p":2,"d":"WALLACE, C.J. (BAR) \u2014 Layup Made (1/2 -  2 pt)"},{"e":820,"s":1580,"a":30,"b":16,"w":0.7781,"p":2,"d":"MICKEAL, PETE (BAR) \u2014 Three Pointer (1/1 -  5 pt)"},{"e":840,"s":1560,"a":32,"b":20,"w":0.747,"p":2,"d":"NDONG, BONIFACE (BAR) \u2014 Dunk (1/2 -  2 pt)"},{"e":843,"s":1557,"a":30,"b":18,"w":0.7472,"p":2,"d":"BLAZIC, JAKA (LJU) \u2014 Two Pointer (1/1 -  2 pt)"},{"e":880,"s":1520,"a":30,"b":20,"w":0.7138,"p":2,"d":"THOMPSON, DEON (LJU) \u2014 Dunk (1/2 -  2 pt)"},{"e":943,"s":1457,"a":33,"b":20,"w":0.7709,"p":2,"d":"INGLES, JOE (BAR) \u2014 Free Throw In (1/1 -  1 pt)"},{"e":943,"s":1457,"a":34,"b":20,"w":0.787,"p":2,"d":"INGLES, JOE (BAR) \u2014 Free Throw In (2/2 -  2 pt)"},{"e":961,"s":1439,"a":34,"b":21,"w":0.7722,"p":2,"d":"VARDA, RATKO (LJU) \u2014 Free Throw In (1/2 -  1 pt)"},{"e":988,"s":1412,"a":34,"b":24,"w":0.7207,"p":2,"d":"WOODSIDE, BEN (LJU) \u2014 Three Pointer (1/1 -  3 pt)"},{"e":1033,"s":1367,"a":37,"b":24,"w":0.7778,"p":2,"d":"NAVARRO, JUAN CARLOS (BAR) \u2014 Three Pointer (2/3 -  10 pt)"},{"e":1097,"s":1303,"a":37,"b":26,"w":0.7476,"p":2,"d":"THOMPSON, DEON (LJU) \u2014 Dunk (2/4 -  4 pt)"},{"e":1152,"s":1248,"a":40,"b":26,"w":0.8041,"p":2,"d":"MICKEAL, PETE (BAR) \u2014 Three Pointer (2/2 -  8 pt)"},{"e":1218,"s":1182,"a":42,"b":26,"w":0.84,"p":3,"d":"PEROVIC, KOSTA (BAR) \u2014 Dunk (3/5 -  10 pt)"},{"e":1293,"s":1107,"a":42,"b":28,"w":0.8175,"p":3,"d":"GREEN, DANNY (LJU) \u2014 Layup Made (5/10 -  10 pt)"},{"e":1314,"s":1086,"a":44,"b":28,"w":0.8494,"p":3,"d":"LORBEK, ERAZEM (BAR) \u2014 Layup Made (2/4 -  4 pt)"},{"e":1333,"s":1067,"a":44,"b":30,"w":0.8216,"p":3,"d":"VARDA, RATKO (LJU) \u2014 Dunk (1/4 -  3 pt)"},{"e":1406,"s":994,"a":46,"b":30,"w":0.8591,"p":3,"d":"NAVARRO, JUAN CARLOS (BAR) \u2014 Layup Made (3/5 -  12 pt)"},{"e":1467,"s":933,"a":48,"b":30,"w":0.8909,"p":3,"d":"NAVARRO, JUAN CARLOS (BAR) \u2014 Layup Made (4/6 -  14 pt)"},{"e":1485,"s":915,"a":50,"b":30,"w":0.9134,"p":3,"d":"PEROVIC, KOSTA (BAR) \u2014 Dunk (4/7 -  12 pt)"},{"e":1504,"s":896,"a":51,"b":30,"w":0.9241,"p":3,"d":"EIDSON, CHUCK (BAR) \u2014 Free Throw In (1/1 -  1 pt)"},{"e":1504,"s":896,"a":52,"b":30,"w":0.9321,"p":3,"d":"EIDSON, CHUCK (BAR) \u2014 Free Throw In (2/2 -  2 pt)"},{"e":1541,"s":859,"a":55,"b":30,"w":0.9543,"p":3,"d":"HUERTAS, MARCELINHO (BAR) \u2014 Three Pointer (1/2 -  7 pt)"},{"e":1554,"s":846,"a":55,"b":32,"w":0.9436,"p":3,"d":"BLAZIC, JAKA (LJU) \u2014 Two Pointer (2/2 -  4 pt)"},{"e":1584,"s":816,"a":56,"b":32,"w":0.9523,"p":3,"d":"EIDSON, CHUCK (BAR) \u2014 Free Throw In (3/3 -  3 pt)"},{"e":1605,"s":795,"a":58,"b":32,"w":0.9639,"p":3,"d":"EIDSON, CHUCK (BAR) \u2014 Dunk (1/3 -  5 pt)"},{"e":1650,"s":750,"a":59,"b":32,"w":0.971,"p":3,"d":"HUERTAS, MARCELINHO (BAR) \u2014 Free Throw In (1/1 -  8 pt)"},{"e":1650,"s":750,"a":60,"b":32,"w":0.9745,"p":3,"d":"HUERTAS, MARCELINHO (BAR) \u2014 Free Throw In (2/2 -  9 pt)"},{"e":1797,"s":603,"a":63,"b":32,"w":0.989,"p":3,"d":"HUERTAS, MARCELINHO (BAR) \u2014 Three Pointer (2/3 -  12 pt)"},{"e":1843,"s":557,"a":63,"b":34,"w":0.9876,"p":4,"d":"SALIN, SASU (LJU) \u2014 Two Pointer (2/2 -  4 pt)"},{"e":1874,"s":526,"a":65,"b":34,"w":0.992,"p":4,"d":"SADA, VICTOR (BAR) \u2014 Layup Made (2/2 -  4 pt)"},{"e":1904,"s":496,"a":65,"b":36,"w":0.9904,"p":4,"d":"THOMPSON, DEON (LJU) \u2014 Layup Made (3/5 -  6 pt)"},{"e":2049,"s":351,"a":67,"b":36,"w":0.9973,"p":4,"d":"VAZQUEZ, FRAN (BAR) \u2014 Layup Made (1/2 -  2 pt)"},{"e":2091,"s":309,"a":67,"b":38,"w":0.9972,"p":4,"d":"THOMPSON, DEON (LJU) \u2014 Dunk (4/7 -  8 pt)"},{"e":2107,"s":293,"a":69,"b":38,"w":0.9984,"p":4,"d":"VAZQUEZ, FRAN (BAR) \u2014 Layup Made (2/3 -  4 pt)"},{"e":2240,"s":160,"a":72,"b":38,"w":0.9999,"p":4,"d":"WALLACE, C.J. (BAR) \u2014 Three Pointer (1/2 -  5 pt)"},{"e":2259,"s":141,"a":72,"b":39,"w":0.9999,"p":4,"d":"MURIC, DINO (LJU) \u2014 Free Throw In (1/1 -  1 pt)"},{"e":2259,"s":141,"a":72,"b":40,"w":0.9999,"p":4,"d":"MURIC, DINO (LJU) \u2014 Free Throw In (2/2 -  2 pt)"},{"e":2322,"s":78,"a":72,"b":42,"w":1.0,"p":4,"d":"CAPIN, ALEKSANDAR (LJU) \u2014 Two Pointer (2/3 -  6 pt)"},{"e":2369,"s":31,"a":72,"b":43,"w":1.0,"p":4,"d":"CAPIN, ALEKSANDAR (LJU) \u2014 Free Throw In (3/3 -  7 pt)"},{"e":2369,"s":31,"a":72,"b":44,"w":1.0,"p":4,"d":"CAPIN, ALEKSANDAR (LJU) \u2014 Free Throw In (4/4 -  8 pt)"},{"e":2392,"s":8,"a":72,"b":45,"w":1.0,"p":4,"d":"CAPIN, ALEKSANDAR (LJU) \u2014 Free Throw In (5/5 -  9 pt)"},{"e":2392,"s":8,"a":72,"b":46,"w":1.0,"p":4,"d":"CAPIN, ALEKSANDAR (LJU) \u2014 Free Throw In (6/6 -  10 pt)"},{"e":2400,"s":0,"a":72,"b":46,"w":1.0,"p":4,"d":"Final Buzzer"}],"adv":{"q":[{"p":1,"a":23,"b":16},{"p":2,"a":17,"b":10},{"p":3,"a":23,"b":6},{"p":4,"a":9,"b":14}],"i":[{"n":"Bertans","p":0,"h":2,"t":"LJU"},{"n":"Blazic","p":4,"h":3,"t":"LJU"},{"n":"Capin","p":8,"h":3,"t":"LJU"},{"n":"Eidson","p":3,"h":11,"t":"BAR"},{"n":"Green","p":8,"h":6,"t":"LJU"},{"n":"Huertas","p":10,"h":7,"t":"BAR"},{"n":"Ingles","p":2,"h":3,"t":"BAR"},{"n":"Lorbek","p":2,"h":9,"t":"BAR"},{"n":"Markota","p":0,"h":2,"t":"LJU"},{"n":"Mickeal","p":8,"h":7,"t":"BAR"},{"n":"Muric","p":2,"h":2,"t":"LJU"},{"n":"Navarro","p":8,"h":1,"t":"BAR"},{"n":"Ndong","p":0,"h":3,"t":"BAR"},{"n":"Perovic","p":4,"h":3,"t":"BAR"},{"n":"Rabaseda","p":0,"h":2,"t":"BAR"},{"n":"Rothbart","p":2,"h":3,"t":"LJU"},{"n":"Sada","p":0,"h":5,"t":"BAR"},{"n":"Salin","p":2,"h":3,"t":"LJU"},{"n":"Thompson","p":0,"h":5,"t":"LJU"},{"n":"Varda","p":1,"h":5,"t":"LJU"},{"n":"Vazquez","p":0,"h":5,"t":"BAR"},{"n":"Wallace","p":3,"h":5,"t":"BAR"},{"n":"Woodside","p":3,"h":6,"t":"LJU"}]}}